<?xml version="1.0" encoding="UTF-8"?>
<DEFECTS>
  <DEFECT>
    <SFA>
      <FILEPATH>E:\XBLAH\content\Mapbase\klepto\src\public\</FILEPATH>
      <FILENAME>bone_setup.h</FILENAME>
      <LINE>252</LINE>
      <COLUMN>1</COLUMN>
    </SFA>
    <DEFECTCODE>26495</DEFECTCODE>
    <DESCRIPTION>Variable 'ikcontextikrule_t::szLabel' is uninitialized. Always initialize a member variable (type.6).</DESCRIPTION>
    <FUNCTION>ikcontextikrule_t::{ctor}</FUNCTION>
    <DECORATED>??0ikcontextikrule_t@@QAE@XZ</DECORATED>
    <FUNCLINE>252</FUNCLINE>
    <ADDITIONALINFO>
      <targetSymbol>ikcontextikrule_t::szLabel</targetSymbol>
    </ADDITIONALINFO>
    <PATH></PATH>
  </DEFECT>
  <DEFECT>
    <SFA>
      <FILEPATH>E:\XBLAH\content\Mapbase\klepto\src\public\</FILEPATH>
      <FILENAME>bone_setup.h</FILENAME>
      <LINE>252</LINE>
      <COLUMN>1</COLUMN>
    </SFA>
    <DEFECTCODE>26495</DEFECTCODE>
    <DESCRIPTION>Variable 'ikcontextikrule_t::latched' is uninitialized. Always initialize a member variable (type.6).</DESCRIPTION>
    <FUNCTION>ikcontextikrule_t::{ctor}</FUNCTION>
    <DECORATED>??0ikcontextikrule_t@@QAE@XZ</DECORATED>
    <FUNCLINE>252</FUNCLINE>
    <ADDITIONALINFO>
      <targetSymbol>ikcontextikrule_t::latched</targetSymbol>
    </ADDITIONALINFO>
    <PATH></PATH>
  </DEFECT>
  <DEFECT>
    <SFA>
      <FILEPATH>E:\XBLAH\content\Mapbase\klepto\src\public\</FILEPATH>
      <FILENAME>bone_setup.h</FILENAME>
      <LINE>252</LINE>
      <COLUMN>1</COLUMN>
    </SFA>
    <DEFECTCODE>26495</DEFECTCODE>
    <DESCRIPTION>Variable 'ikcontextikrule_t::flRuleWeight' is uninitialized. Always initialize a member variable (type.6).</DESCRIPTION>
    <FUNCTION>ikcontextikrule_t::{ctor}</FUNCTION>
    <DECORATED>??0ikcontextikrule_t@@QAE@XZ</DECORATED>
    <FUNCLINE>252</FUNCLINE>
    <ADDITIONALINFO>
      <targetSymbol>ikcontextikrule_t::flRuleWeight</targetSymbol>
    </ADDITIONALINFO>
    <PATH></PATH>
  </DEFECT>
  <DEFECT>
    <SFA>
      <FILEPATH>E:\XBLAH\content\Mapbase\klepto\src\public\</FILEPATH>
      <FILENAME>bone_setup.h</FILENAME>
      <LINE>252</LINE>
      <COLUMN>1</COLUMN>
    </SFA>
    <DEFECTCODE>26495</DEFECTCODE>
    <DESCRIPTION>Variable 'ikcontextikrule_t::flWeight' is uninitialized. Always initialize a member variable (type.6).</DESCRIPTION>
    <FUNCTION>ikcontextikrule_t::{ctor}</FUNCTION>
    <DECORATED>??0ikcontextikrule_t@@QAE@XZ</DECORATED>
    <FUNCLINE>252</FUNCLINE>
    <ADDITIONALINFO>
      <targetSymbol>ikcontextikrule_t::flWeight</targetSymbol>
    </ADDITIONALINFO>
    <PATH></PATH>
  </DEFECT>
  <DEFECT>
    <SFA>
      <FILEPATH>E:\XBLAH\content\Mapbase\klepto\src\public\</FILEPATH>
      <FILENAME>bone_setup.h</FILENAME>
      <LINE>252</LINE>
      <COLUMN>1</COLUMN>
    </SFA>
    <DEFECTCODE>26495</DEFECTCODE>
    <DESCRIPTION>Variable 'ikcontextikrule_t::release' is uninitialized. Always initialize a member variable (type.6).</DESCRIPTION>
    <FUNCTION>ikcontextikrule_t::{ctor}</FUNCTION>
    <DECORATED>??0ikcontextikrule_t@@QAE@XZ</DECORATED>
    <FUNCLINE>252</FUNCLINE>
    <ADDITIONALINFO>
      <targetSymbol>ikcontextikrule_t::release</targetSymbol>
    </ADDITIONALINFO>
    <PATH></PATH>
  </DEFECT>
  <DEFECT>
    <SFA>
      <FILEPATH>E:\XBLAH\content\Mapbase\klepto\src\public\</FILEPATH>
      <FILENAME>bone_setup.h</FILENAME>
      <LINE>252</LINE>
      <COLUMN>1</COLUMN>
    </SFA>
    <DEFECTCODE>26495</DEFECTCODE>
    <DESCRIPTION>Variable 'ikcontextikrule_t::drop' is uninitialized. Always initialize a member variable (type.6).</DESCRIPTION>
    <FUNCTION>ikcontextikrule_t::{ctor}</FUNCTION>
    <DECORATED>??0ikcontextikrule_t@@QAE@XZ</DECORATED>
    <FUNCLINE>252</FUNCLINE>
    <ADDITIONALINFO>
      <targetSymbol>ikcontextikrule_t::drop</targetSymbol>
    </ADDITIONALINFO>
    <PATH></PATH>
  </DEFECT>
  <DEFECT>
    <SFA>
      <FILEPATH>E:\XBLAH\content\Mapbase\klepto\src\public\</FILEPATH>
      <FILENAME>bone_setup.h</FILENAME>
      <LINE>252</LINE>
      <COLUMN>1</COLUMN>
    </SFA>
    <DEFECTCODE>26495</DEFECTCODE>
    <DESCRIPTION>Variable 'ikcontextikrule_t::commit' is uninitialized. Always initialize a member variable (type.6).</DESCRIPTION>
    <FUNCTION>ikcontextikrule_t::{ctor}</FUNCTION>
    <DECORATED>??0ikcontextikrule_t@@QAE@XZ</DECORATED>
    <FUNCLINE>252</FUNCLINE>
    <ADDITIONALINFO>
      <targetSymbol>ikcontextikrule_t::commit</targetSymbol>
    </ADDITIONALINFO>
    <PATH></PATH>
  </DEFECT>
  <DEFECT>
    <SFA>
      <FILEPATH>E:\XBLAH\content\Mapbase\klepto\src\public\</FILEPATH>
      <FILENAME>bone_setup.h</FILENAME>
      <LINE>252</LINE>
      <COLUMN>1</COLUMN>
    </SFA>
    <DEFECTCODE>26495</DEFECTCODE>
    <DESCRIPTION>Variable 'ikcontextikrule_t::tail' is uninitialized. Always initialize a member variable (type.6).</DESCRIPTION>
    <FUNCTION>ikcontextikrule_t::{ctor}</FUNCTION>
    <DECORATED>??0ikcontextikrule_t@@QAE@XZ</DECORATED>
    <FUNCLINE>252</FUNCLINE>
    <ADDITIONALINFO>
      <targetSymbol>ikcontextikrule_t::tail</targetSymbol>
    </ADDITIONALINFO>
    <PATH></PATH>
  </DEFECT>
  <DEFECT>
    <SFA>
      <FILEPATH>E:\XBLAH\content\Mapbase\klepto\src\public\</FILEPATH>
      <FILENAME>bone_setup.h</FILENAME>
      <LINE>252</LINE>
      <COLUMN>1</COLUMN>
    </SFA>
    <DEFECTCODE>26495</DEFECTCODE>
    <DESCRIPTION>Variable 'ikcontextikrule_t::peak' is uninitialized. Always initialize a member variable (type.6).</DESCRIPTION>
    <FUNCTION>ikcontextikrule_t::{ctor}</FUNCTION>
    <DECORATED>??0ikcontextikrule_t@@QAE@XZ</DECORATED>
    <FUNCLINE>252</FUNCLINE>
    <ADDITIONALINFO>
      <targetSymbol>ikcontextikrule_t::peak</targetSymbol>
    </ADDITIONALINFO>
    <PATH></PATH>
  </DEFECT>
  <DEFECT>
    <SFA>
      <FILEPATH>E:\XBLAH\content\Mapbase\klepto\src\public\</FILEPATH>
      <FILENAME>bone_setup.h</FILENAME>
      <LINE>252</LINE>
      <COLUMN>1</COLUMN>
    </SFA>
    <DEFECTCODE>26495</DEFECTCODE>
    <DESCRIPTION>Variable 'ikcontextikrule_t::top' is uninitialized. Always initialize a member variable (type.6).</DESCRIPTION>
    <FUNCTION>ikcontextikrule_t::{ctor}</FUNCTION>
    <DECORATED>??0ikcontextikrule_t@@QAE@XZ</DECORATED>
    <FUNCLINE>252</FUNCLINE>
    <ADDITIONALINFO>
      <targetSymbol>ikcontextikrule_t::top</targetSymbol>
    </ADDITIONALINFO>
    <PATH></PATH>
  </DEFECT>
  <DEFECT>
    <SFA>
      <FILEPATH>E:\XBLAH\content\Mapbase\klepto\src\public\</FILEPATH>
      <FILENAME>bone_setup.h</FILENAME>
      <LINE>252</LINE>
      <COLUMN>1</COLUMN>
    </SFA>
    <DEFECTCODE>26495</DEFECTCODE>
    <DESCRIPTION>Variable 'ikcontextikrule_t::end' is uninitialized. Always initialize a member variable (type.6).</DESCRIPTION>
    <FUNCTION>ikcontextikrule_t::{ctor}</FUNCTION>
    <DECORATED>??0ikcontextikrule_t@@QAE@XZ</DECORATED>
    <FUNCLINE>252</FUNCLINE>
    <ADDITIONALINFO>
      <targetSymbol>ikcontextikrule_t::end</targetSymbol>
    </ADDITIONALINFO>
    <PATH></PATH>
  </DEFECT>
  <DEFECT>
    <SFA>
      <FILEPATH>E:\XBLAH\content\Mapbase\klepto\src\public\</FILEPATH>
      <FILENAME>bone_setup.h</FILENAME>
      <LINE>252</LINE>
      <COLUMN>1</COLUMN>
    </SFA>
    <DEFECTCODE>26495</DEFECTCODE>
    <DESCRIPTION>Variable 'ikcontextikrule_t::start' is uninitialized. Always initialize a member variable (type.6).</DESCRIPTION>
    <FUNCTION>ikcontextikrule_t::{ctor}</FUNCTION>
    <DECORATED>??0ikcontextikrule_t@@QAE@XZ</DECORATED>
    <FUNCLINE>252</FUNCLINE>
    <ADDITIONALINFO>
      <targetSymbol>ikcontextikrule_t::start</targetSymbol>
    </ADDITIONALINFO>
    <PATH></PATH>
  </DEFECT>
  <DEFECT>
    <SFA>
      <FILEPATH>E:\XBLAH\content\Mapbase\klepto\src\public\</FILEPATH>
      <FILENAME>bone_setup.h</FILENAME>
      <LINE>252</LINE>
      <COLUMN>1</COLUMN>
    </SFA>
    <DEFECTCODE>26495</DEFECTCODE>
    <DESCRIPTION>Variable 'ikcontextikrule_t::index' is uninitialized. Always initialize a member variable (type.6).</DESCRIPTION>
    <FUNCTION>ikcontextikrule_t::{ctor}</FUNCTION>
    <DECORATED>??0ikcontextikrule_t@@QAE@XZ</DECORATED>
    <FUNCLINE>252</FUNCLINE>
    <ADDITIONALINFO>
      <targetSymbol>ikcontextikrule_t::index</targetSymbol>
    </ADDITIONALINFO>
    <PATH></PATH>
  </DEFECT>
  <DEFECT>
    <SFA>
      <FILEPATH>E:\XBLAH\content\Mapbase\klepto\src\public\</FILEPATH>
      <FILENAME>bone_setup.h</FILENAME>
      <LINE>252</LINE>
      <COLUMN>1</COLUMN>
    </SFA>
    <DEFECTCODE>26495</DEFECTCODE>
    <DESCRIPTION>Variable 'ikcontextikrule_t::type' is uninitialized. Always initialize a member variable (type.6).</DESCRIPTION>
    <FUNCTION>ikcontextikrule_t::{ctor}</FUNCTION>
    <DECORATED>??0ikcontextikrule_t@@QAE@XZ</DECORATED>
    <FUNCLINE>252</FUNCLINE>
    <ADDITIONALINFO>
      <targetSymbol>ikcontextikrule_t::type</targetSymbol>
    </ADDITIONALINFO>
    <PATH></PATH>
  </DEFECT>
  <DEFECT>
    <SFA>
      <FILEPATH>E:\XBLAH\content\Mapbase\klepto\src\public\</FILEPATH>
      <FILENAME>bone_setup.h</FILENAME>
      <LINE>252</LINE>
      <COLUMN>1</COLUMN>
    </SFA>
    <DEFECTCODE>26495</DEFECTCODE>
    <DESCRIPTION>Variable 'ikcontextikrule_t::chain' is uninitialized. Always initialize a member variable (type.6).</DESCRIPTION>
    <FUNCTION>ikcontextikrule_t::{ctor}</FUNCTION>
    <DECORATED>??0ikcontextikrule_t@@QAE@XZ</DECORATED>
    <FUNCLINE>252</FUNCLINE>
    <ADDITIONALINFO>
      <targetSymbol>ikcontextikrule_t::chain</targetSymbol>
    </ADDITIONALINFO>
    <PATH></PATH>
  </DEFECT>
  <DEFECT>
    <SFA>
      <FILEPATH>E:\XBLAH\content\Mapbase\klepto\src\public\</FILEPATH>
      <FILENAME>bone_setup.h</FILENAME>
      <LINE>252</LINE>
      <COLUMN>1</COLUMN>
    </SFA>
    <DEFECTCODE>26495</DEFECTCODE>
    <DESCRIPTION>Variable 'ikcontextikrule_t::bone' is uninitialized. Always initialize a member variable (type.6).</DESCRIPTION>
    <FUNCTION>ikcontextikrule_t::{ctor}</FUNCTION>
    <DECORATED>??0ikcontextikrule_t@@QAE@XZ</DECORATED>
    <FUNCLINE>252</FUNCLINE>
    <ADDITIONALINFO>
      <targetSymbol>ikcontextikrule_t::bone</targetSymbol>
    </ADDITIONALINFO>
    <PATH></PATH>
  </DEFECT>
  <DEFECT>
    <SFA>
      <FILEPATH>E:\XBLAH\content\Mapbase\klepto\src\public\</FILEPATH>
      <FILENAME>bone_setup.h</FILENAME>
      <LINE>252</LINE>
      <COLUMN>1</COLUMN>
    </SFA>
    <DEFECTCODE>26495</DEFECTCODE>
    <DESCRIPTION>Variable 'ikcontextikrule_t::slot' is uninitialized. Always initialize a member variable (type.6).</DESCRIPTION>
    <FUNCTION>ikcontextikrule_t::{ctor}</FUNCTION>
    <DECORATED>??0ikcontextikrule_t@@QAE@XZ</DECORATED>
    <FUNCLINE>252</FUNCLINE>
    <ADDITIONALINFO>
      <targetSymbol>ikcontextikrule_t::slot</targetSymbol>
    </ADDITIONALINFO>
    <PATH></PATH>
  </DEFECT>
  <DEFECT>
    <SFA>
      <FILEPATH>E:\XBLAH\content\Mapbase\klepto\src\public\</FILEPATH>
      <FILENAME>bone_setup.h</FILENAME>
      <LINE>252</LINE>
      <COLUMN>1</COLUMN>
    </SFA>
    <DEFECTCODE>26495</DEFECTCODE>
    <DESCRIPTION>Variable 'ikcontextikrule_t::height' is uninitialized. Always initialize a member variable (type.6).</DESCRIPTION>
    <FUNCTION>ikcontextikrule_t::{ctor}</FUNCTION>
    <DECORATED>??0ikcontextikrule_t@@QAE@XZ</DECORATED>
    <FUNCLINE>252</FUNCLINE>
    <ADDITIONALINFO>
      <targetSymbol>ikcontextikrule_t::height</targetSymbol>
    </ADDITIONALINFO>
    <PATH></PATH>
  </DEFECT>
  <DEFECT>
    <SFA>
      <FILEPATH>E:\XBLAH\content\Mapbase\klepto\src\public\</FILEPATH>
      <FILENAME>bone_setup.h</FILENAME>
      <LINE>252</LINE>
      <COLUMN>1</COLUMN>
    </SFA>
    <DEFECTCODE>26495</DEFECTCODE>
    <DESCRIPTION>Variable 'ikcontextikrule_t::radius' is uninitialized. Always initialize a member variable (type.6).</DESCRIPTION>
    <FUNCTION>ikcontextikrule_t::{ctor}</FUNCTION>
    <DECORATED>??0ikcontextikrule_t@@QAE@XZ</DECORATED>
    <FUNCLINE>252</FUNCLINE>
    <ADDITIONALINFO>
      <targetSymbol>ikcontextikrule_t::radius</targetSymbol>
    </ADDITIONALINFO>
    <PATH></PATH>
  </DEFECT>
  <DEFECT>
    <SFA>
      <FILEPATH>E:\XBLAH\content\Mapbase\klepto\src\public\</FILEPATH>
      <FILENAME>bone_setup.h</FILENAME>
      <LINE>252</LINE>
      <COLUMN>1</COLUMN>
    </SFA>
    <DEFECTCODE>26495</DEFECTCODE>
    <DESCRIPTION>Variable 'ikcontextikrule_t::floor' is uninitialized. Always initialize a member variable (type.6).</DESCRIPTION>
    <FUNCTION>ikcontextikrule_t::{ctor}</FUNCTION>
    <DECORATED>??0ikcontextikrule_t@@QAE@XZ</DECORATED>
    <FUNCLINE>252</FUNCLINE>
    <ADDITIONALINFO>
      <targetSymbol>ikcontextikrule_t::floor</targetSymbol>
    </ADDITIONALINFO>
    <PATH></PATH>
  </DEFECT>
  <DEFECT>
    <SFA>
      <FILEPATH>E:\XBLAH\content\Mapbase\klepto\src\game\server\</FILEPATH>
      <FILENAME>ai_namespaces.h</FILENAME>
      <LINE>141</LINE>
      <COLUMN>1</COLUMN>
    </SFA>
    <DEFECTCODE>26495</DEFECTCODE>
    <DESCRIPTION>Variable 'CAI_ClassScheduleIdSpace::m_pszClassName' is uninitialized. Always initialize a member variable (type.6).</DESCRIPTION>
    <FUNCTION>CAI_ClassScheduleIdSpace::{ctor}</FUNCTION>
    <DECORATED>??0CAI_ClassScheduleIdSpace@@QAE@_N@Z</DECORATED>
    <FUNCLINE>141</FUNCLINE>
    <ADDITIONALINFO>
      <targetSymbol>CAI_ClassScheduleIdSpace::m_pszClassName</targetSymbol>
    </ADDITIONALINFO>
    <PATH></PATH>
  </DEFECT>
  <DEFECT>
    <SFA>
      <FILEPATH>E:\XBLAH\content\Mapbase\klepto\src\game\shared\</FILEPATH>
      <FILENAME>activitylist.h</FILENAME>
      <LINE>22</LINE>
      <COLUMN>1</COLUMN>
    </SFA>
    <DEFECTCODE>26495</DEFECTCODE>
    <DESCRIPTION>Variable 'CActivityRemap::mappedActivity' is uninitialized. Always initialize a member variable (type.6).</DESCRIPTION>
    <FUNCTION>CActivityRemap::{ctor}</FUNCTION>
    <DECORATED>??0CActivityRemap@@QAE@XZ</DECORATED>
    <FUNCLINE>22</FUNCLINE>
    <ADDITIONALINFO>
      <targetSymbol>CActivityRemap::mappedActivity</targetSymbol>
    </ADDITIONALINFO>
    <PATH></PATH>
  </DEFECT>
  <DEFECT>
    <SFA>
      <FILEPATH>E:\XBLAH\content\Mapbase\klepto\src\game\shared\</FILEPATH>
      <FILENAME>activitylist.h</FILENAME>
      <LINE>22</LINE>
      <COLUMN>1</COLUMN>
    </SFA>
    <DEFECTCODE>26495</DEFECTCODE>
    <DESCRIPTION>Variable 'CActivityRemap::activity' is uninitialized. Always initialize a member variable (type.6).</DESCRIPTION>
    <FUNCTION>CActivityRemap::{ctor}</FUNCTION>
    <DECORATED>??0CActivityRemap@@QAE@XZ</DECORATED>
    <FUNCLINE>22</FUNCLINE>
    <ADDITIONALINFO>
      <targetSymbol>CActivityRemap::activity</targetSymbol>
    </ADDITIONALINFO>
    <PATH></PATH>
  </DEFECT>
  <DEFECT>
    <SFA>
      <FILEPATH>E:\XBLAH\content\Mapbase\klepto\src\game\server\</FILEPATH>
      <FILENAME>BaseAnimatingOverlay.cpp</FILENAME>
      <LINE>259</LINE>
      <COLUMN>3</COLUMN>
    </SFA>
    <DEFECTCODE>6385</DEFECTCODE>
    <DESCRIPTION>Reading invalid data from 'layer':  the readable size is '60' bytes, but 'j' bytes may be read.</DESCRIPTION>
    <FUNCTION>CBaseAnimatingOverlay::VerifyOrder</FUNCTION>
    <DECORATED>?VerifyOrder@CBaseAnimatingOverlay@@QAEXXZ</DECORATED>
    <FUNCLINE>243</FUNCLINE>
    <PROBABILITY>1</PROBABILITY>
    <RANK>4</RANK>
    <CATEGORY>
      <RULECATEGORY>mspft</RULECATEGORY>
    </CATEGORY>
    <PATH>
      <SFA>
        <FILEPATH>E:\XBLAH\content\Mapbase\klepto\src\game\server\</FILEPATH>
        <FILENAME>BaseAnimatingOverlay.cpp</FILENAME>
        <LINE>246</LINE>
        <COLUMN>5</COLUMN>
      </SFA>
      <SFA>
        <FILEPATH>E:\XBLAH\content\Mapbase\klepto\src\game\server\</FILEPATH>
        <FILENAME>BaseAnimatingOverlay.cpp</FILENAME>
        <LINE>246</LINE>
        <COLUMN>8</COLUMN>
      </SFA>
      <SFA>
        <FILEPATH>E:\XBLAH\content\Mapbase\klepto\src\game\server\</FILEPATH>
        <FILENAME>BaseAnimatingOverlay.cpp</FILENAME>
        <LINE>248</LINE>
        <COLUMN>5</COLUMN>
        <KEYEVENT>
          <ID>1</ID>
          <KIND>declaration</KIND>
          <IMPORTANCE>Essential</IMPORTANCE>
          <MESSAGE>'layer' is an array of 15 elements (60 bytes)</MESSAGE>
        </KEYEVENT>
      </SFA>
      <SFA>
        <FILEPATH>E:\XBLAH\content\Mapbase\klepto\src\game\server\</FILEPATH>
        <FILENAME>BaseAnimatingOverlay.cpp</FILENAME>
        <LINE>249</LINE>
        <COLUMN>5</COLUMN>
      </SFA>
      <SFA>
        <FILEPATH>E:\XBLAH\content\Mapbase\klepto\src\game\server\</FILEPATH>
        <FILENAME>BaseAnimatingOverlay.cpp</FILENAME>
        <LINE>250</LINE>
        <COLUMN>8</COLUMN>
      </SFA>
      <SFA>
        <FILEPATH>E:\XBLAH\content\Mapbase\klepto\src\game\server\</FILEPATH>
        <FILENAME>BaseAnimatingOverlay.cpp</FILENAME>
        <LINE>250</LINE>
        <COLUMN>15</COLUMN>
      </SFA>
      <SFA>
        <FILEPATH>E:\XBLAH\content\Mapbase\klepto\src\game\server\</FILEPATH>
        <FILENAME>BaseAnimatingOverlay.cpp</FILENAME>
        <LINE>252</LINE>
        <COLUMN>11</COLUMN>
      </SFA>
      <SFA>
        <FILEPATH>E:\XBLAH\content\Mapbase\klepto\src\game\server\</FILEPATH>
        <FILENAME>BaseAnimatingOverlay.cpp</FILENAME>
        <LINE>250</LINE>
        <COLUMN>32</COLUMN>
      </SFA>
      <SFA>
        <FILEPATH>E:\XBLAH\content\Mapbase\klepto\src\game\server\</FILEPATH>
        <FILENAME>BaseAnimatingOverlay.cpp</FILENAME>
        <LINE>250</LINE>
        <COLUMN>15</COLUMN>
      </SFA>
      <SFA>
        <FILEPATH>E:\XBLAH\content\Mapbase\klepto\src\game\server\</FILEPATH>
        <FILENAME>BaseAnimatingOverlay.cpp</FILENAME>
        <LINE>252</LINE>
        <COLUMN>11</COLUMN>
      </SFA>
      <SFA>
        <FILEPATH>E:\XBLAH\content\Mapbase\klepto\src\game\server\</FILEPATH>
        <FILENAME>BaseAnimatingOverlay.cpp</FILENAME>
        <LINE>250</LINE>
        <COLUMN>32</COLUMN>
      </SFA>
      <SFA>
        <FILEPATH>E:\XBLAH\content\Mapbase\klepto\src\game\server\</FILEPATH>
        <FILENAME>BaseAnimatingOverlay.cpp</FILENAME>
        <LINE>250</LINE>
        <COLUMN>15</COLUMN>
      </SFA>
      <SFA>
        <FILEPATH>E:\XBLAH\content\Mapbase\klepto\src\game\server\</FILEPATH>
        <FILENAME>BaseAnimatingOverlay.cpp</FILENAME>
        <LINE>254</LINE>
        <COLUMN>8</COLUMN>
      </SFA>
      <SFA>
        <FILEPATH>E:\XBLAH\content\Mapbase\klepto\src\game\server\</FILEPATH>
        <FILENAME>BaseAnimatingOverlay.cpp</FILENAME>
        <LINE>254</LINE>
        <COLUMN>15</COLUMN>
        <KEYEVENT>
          <ID>2</ID>
          <KIND>branch</KIND>
          <IMPORTANCE>Full</IMPORTANCE>
          <MESSAGE>Enter this loop, (assume 'i&lt;m_AnimOverlay.Count()')</MESSAGE>
        </KEYEVENT>
      </SFA>
      <SFA>
        <FILEPATH>E:\XBLAH\content\Mapbase\klepto\src\game\server\</FILEPATH>
        <FILENAME>BaseAnimatingOverlay.cpp</FILENAME>
        <LINE>256</LINE>
        <COLUMN>34</COLUMN>
        <KEYEVENT>
          <ID>3</ID>
          <KIND>branch</KIND>
          <IMPORTANCE>Full</IMPORTANCE>
          <MESSAGE>Enter this branch, (assume '&lt;branch condition&gt;')</MESSAGE>
        </KEYEVENT>
      </SFA>
      <SFA>
        <FILEPATH>E:\XBLAH\content\Mapbase\klepto\src\game\server\</FILEPATH>
        <FILENAME>BaseAnimatingOverlay.cpp</FILENAME>
        <LINE>258</LINE>
        <COLUMN>5</COLUMN>
      </SFA>
      <SFA>
        <FILEPATH>E:\XBLAH\content\Mapbase\klepto\src\game\server\</FILEPATH>
        <FILENAME>BaseAnimatingOverlay.cpp</FILENAME>
        <LINE>259</LINE>
        <COLUMN>3</COLUMN>
      </SFA>
      <SFA>
        <FILEPATH>E:\XBLAH\content\Mapbase\klepto\src\game\server\</FILEPATH>
        <FILENAME>BaseAnimatingOverlay.cpp</FILENAME>
        <LINE>260</LINE>
        <COLUMN>12</COLUMN>
      </SFA>
      <SFA>
        <FILEPATH>E:\XBLAH\content\Mapbase\klepto\src\game\server\</FILEPATH>
        <FILENAME>BaseAnimatingOverlay.cpp</FILENAME>
        <LINE>261</LINE>
        <COLUMN>9</COLUMN>
        <KEYEVENT>
          <ID>4</ID>
          <KIND>branch</KIND>
          <IMPORTANCE>Full</IMPORTANCE>
          <MESSAGE>Skip this branch, (assume 'j&gt;maxOrder' is false)</MESSAGE>
        </KEYEVENT>
      </SFA>
      <SFA>
        <FILEPATH>E:\XBLAH\content\Mapbase\klepto\src\game\server\</FILEPATH>
        <FILENAME>BaseAnimatingOverlay.cpp</FILENAME>
        <LINE>254</LINE>
        <COLUMN>41</COLUMN>
      </SFA>
      <SFA>
        <FILEPATH>E:\XBLAH\content\Mapbase\klepto\src\game\server\</FILEPATH>
        <FILENAME>BaseAnimatingOverlay.cpp</FILENAME>
        <LINE>254</LINE>
        <COLUMN>15</COLUMN>
        <KEYEVENT>
          <ID>5</ID>
          <KIND>branch</KIND>
          <IMPORTANCE>Full</IMPORTANCE>
          <MESSAGE>Continue this loop, (assume 'i&lt;m_AnimOverlay.Count()')</MESSAGE>
        </KEYEVENT>
      </SFA>
      <SFA>
        <FILEPATH>E:\XBLAH\content\Mapbase\klepto\src\game\server\</FILEPATH>
        <FILENAME>BaseAnimatingOverlay.cpp</FILENAME>
        <LINE>256</LINE>
        <COLUMN>34</COLUMN>
        <KEYEVENT>
          <ID>6</ID>
          <KIND>branch</KIND>
          <IMPORTANCE>Full</IMPORTANCE>
          <MESSAGE>Enter this branch, (assume '&lt;branch condition&gt;')</MESSAGE>
        </KEYEVENT>
      </SFA>
      <SFA>
        <FILEPATH>E:\XBLAH\content\Mapbase\klepto\src\game\server\</FILEPATH>
        <FILENAME>BaseAnimatingOverlay.cpp</FILENAME>
        <LINE>258</LINE>
        <COLUMN>5</COLUMN>
      </SFA>
      <SFA>
        <FILEPATH>E:\XBLAH\content\Mapbase\klepto\src\game\server\</FILEPATH>
        <FILENAME>BaseAnimatingOverlay.cpp</FILENAME>
        <LINE>259</LINE>
        <COLUMN>3</COLUMN>
        <KEYEVENT>
          <ID>7</ID>
          <KIND>usage</KIND>
          <IMPORTANCE>Essential</IMPORTANCE>
          <MESSAGE>Invalid read from 'layer[-1]', (readable range is 0 to 14)</MESSAGE>
        </KEYEVENT>
      </SFA>
    </PATH>
  </DEFECT>
  <DEFECT>
    <SFA>
      <FILEPATH>E:\XBLAH\content\Mapbase\klepto\src\game\server\</FILEPATH>
      <FILENAME>BaseAnimatingOverlay.cpp</FILENAME>
      <LINE>260</LINE>
      <COLUMN>12</COLUMN>
    </SFA>
    <DEFECTCODE>6386</DEFECTCODE>
    <DESCRIPTION>Buffer overrun while writing to 'layer':  the writable size is '60' bytes, but 'j' bytes might be written.</DESCRIPTION>
    <FUNCTION>CBaseAnimatingOverlay::VerifyOrder</FUNCTION>
    <DECORATED>?VerifyOrder@CBaseAnimatingOverlay@@QAEXXZ</DECORATED>
    <FUNCLINE>243</FUNCLINE>
    <PROBABILITY>1</PROBABILITY>
    <RANK>4</RANK>
    <CATEGORY>
      <RULECATEGORY>mspft</RULECATEGORY>
    </CATEGORY>
    <PATH>
      <SFA>
        <FILEPATH>E:\XBLAH\content\Mapbase\klepto\src\game\server\</FILEPATH>
        <FILENAME>BaseAnimatingOverlay.cpp</FILENAME>
        <LINE>246</LINE>
        <COLUMN>5</COLUMN>
      </SFA>
      <SFA>
        <FILEPATH>E:\XBLAH\content\Mapbase\klepto\src\game\server\</FILEPATH>
        <FILENAME>BaseAnimatingOverlay.cpp</FILENAME>
        <LINE>246</LINE>
        <COLUMN>8</COLUMN>
      </SFA>
      <SFA>
        <FILEPATH>E:\XBLAH\content\Mapbase\klepto\src\game\server\</FILEPATH>
        <FILENAME>BaseAnimatingOverlay.cpp</FILENAME>
        <LINE>248</LINE>
        <COLUMN>5</COLUMN>
        <KEYEVENT>
          <ID>1</ID>
          <KIND>declaration</KIND>
          <IMPORTANCE>Essential</IMPORTANCE>
          <MESSAGE>'layer' is an array of 15 elements (60 bytes)</MESSAGE>
        </KEYEVENT>
      </SFA>
      <SFA>
        <FILEPATH>E:\XBLAH\content\Mapbase\klepto\src\game\server\</FILEPATH>
        <FILENAME>BaseAnimatingOverlay.cpp</FILENAME>
        <LINE>249</LINE>
        <COLUMN>5</COLUMN>
      </SFA>
      <SFA>
        <FILEPATH>E:\XBLAH\content\Mapbase\klepto\src\game\server\</FILEPATH>
        <FILENAME>BaseAnimatingOverlay.cpp</FILENAME>
        <LINE>250</LINE>
        <COLUMN>8</COLUMN>
      </SFA>
      <SFA>
        <FILEPATH>E:\XBLAH\content\Mapbase\klepto\src\game\server\</FILEPATH>
        <FILENAME>BaseAnimatingOverlay.cpp</FILENAME>
        <LINE>250</LINE>
        <COLUMN>15</COLUMN>
      </SFA>
      <SFA>
        <FILEPATH>E:\XBLAH\content\Mapbase\klepto\src\game\server\</FILEPATH>
        <FILENAME>BaseAnimatingOverlay.cpp</FILENAME>
        <LINE>252</LINE>
        <COLUMN>11</COLUMN>
      </SFA>
      <SFA>
        <FILEPATH>E:\XBLAH\content\Mapbase\klepto\src\game\server\</FILEPATH>
        <FILENAME>BaseAnimatingOverlay.cpp</FILENAME>
        <LINE>250</LINE>
        <COLUMN>32</COLUMN>
      </SFA>
      <SFA>
        <FILEPATH>E:\XBLAH\content\Mapbase\klepto\src\game\server\</FILEPATH>
        <FILENAME>BaseAnimatingOverlay.cpp</FILENAME>
        <LINE>250</LINE>
        <COLUMN>15</COLUMN>
      </SFA>
      <SFA>
        <FILEPATH>E:\XBLAH\content\Mapbase\klepto\src\game\server\</FILEPATH>
        <FILENAME>BaseAnimatingOverlay.cpp</FILENAME>
        <LINE>252</LINE>
        <COLUMN>11</COLUMN>
      </SFA>
      <SFA>
        <FILEPATH>E:\XBLAH\content\Mapbase\klepto\src\game\server\</FILEPATH>
        <FILENAME>BaseAnimatingOverlay.cpp</FILENAME>
        <LINE>250</LINE>
        <COLUMN>32</COLUMN>
      </SFA>
      <SFA>
        <FILEPATH>E:\XBLAH\content\Mapbase\klepto\src\game\server\</FILEPATH>
        <FILENAME>BaseAnimatingOverlay.cpp</FILENAME>
        <LINE>250</LINE>
        <COLUMN>15</COLUMN>
      </SFA>
      <SFA>
        <FILEPATH>E:\XBLAH\content\Mapbase\klepto\src\game\server\</FILEPATH>
        <FILENAME>BaseAnimatingOverlay.cpp</FILENAME>
        <LINE>254</LINE>
        <COLUMN>8</COLUMN>
      </SFA>
      <SFA>
        <FILEPATH>E:\XBLAH\content\Mapbase\klepto\src\game\server\</FILEPATH>
        <FILENAME>BaseAnimatingOverlay.cpp</FILENAME>
        <LINE>254</LINE>
        <COLUMN>15</COLUMN>
        <KEYEVENT>
          <ID>2</ID>
          <KIND>branch</KIND>
          <IMPORTANCE>Full</IMPORTANCE>
          <MESSAGE>Enter this loop, (assume 'i&lt;m_AnimOverlay.Count()')</MESSAGE>
        </KEYEVENT>
      </SFA>
      <SFA>
        <FILEPATH>E:\XBLAH\content\Mapbase\klepto\src\game\server\</FILEPATH>
        <FILENAME>BaseAnimatingOverlay.cpp</FILENAME>
        <LINE>256</LINE>
        <COLUMN>34</COLUMN>
        <KEYEVENT>
          <ID>3</ID>
          <KIND>branch</KIND>
          <IMPORTANCE>Full</IMPORTANCE>
          <MESSAGE>Enter this branch, (assume '&lt;branch condition&gt;')</MESSAGE>
        </KEYEVENT>
      </SFA>
      <SFA>
        <FILEPATH>E:\XBLAH\content\Mapbase\klepto\src\game\server\</FILEPATH>
        <FILENAME>BaseAnimatingOverlay.cpp</FILENAME>
        <LINE>258</LINE>
        <COLUMN>5</COLUMN>
      </SFA>
      <SFA>
        <FILEPATH>E:\XBLAH\content\Mapbase\klepto\src\game\server\</FILEPATH>
        <FILENAME>BaseAnimatingOverlay.cpp</FILENAME>
        <LINE>259</LINE>
        <COLUMN>3</COLUMN>
      </SFA>
      <SFA>
        <FILEPATH>E:\XBLAH\content\Mapbase\klepto\src\game\server\</FILEPATH>
        <FILENAME>BaseAnimatingOverlay.cpp</FILENAME>
        <LINE>260</LINE>
        <COLUMN>12</COLUMN>
      </SFA>
      <SFA>
        <FILEPATH>E:\XBLAH\content\Mapbase\klepto\src\game\server\</FILEPATH>
        <FILENAME>BaseAnimatingOverlay.cpp</FILENAME>
        <LINE>261</LINE>
        <COLUMN>9</COLUMN>
        <KEYEVENT>
          <ID>4</ID>
          <KIND>branch</KIND>
          <IMPORTANCE>Full</IMPORTANCE>
          <MESSAGE>Skip this branch, (assume 'j&gt;maxOrder' is false)</MESSAGE>
        </KEYEVENT>
      </SFA>
      <SFA>
        <FILEPATH>E:\XBLAH\content\Mapbase\klepto\src\game\server\</FILEPATH>
        <FILENAME>BaseAnimatingOverlay.cpp</FILENAME>
        <LINE>254</LINE>
        <COLUMN>41</COLUMN>
      </SFA>
      <SFA>
        <FILEPATH>E:\XBLAH\content\Mapbase\klepto\src\game\server\</FILEPATH>
        <FILENAME>BaseAnimatingOverlay.cpp</FILENAME>
        <LINE>254</LINE>
        <COLUMN>15</COLUMN>
        <KEYEVENT>
          <ID>5</ID>
          <KIND>branch</KIND>
          <IMPORTANCE>Full</IMPORTANCE>
          <MESSAGE>Continue this loop, (assume 'i&lt;m_AnimOverlay.Count()')</MESSAGE>
        </KEYEVENT>
      </SFA>
      <SFA>
        <FILEPATH>E:\XBLAH\content\Mapbase\klepto\src\game\server\</FILEPATH>
        <FILENAME>BaseAnimatingOverlay.cpp</FILENAME>
        <LINE>256</LINE>
        <COLUMN>34</COLUMN>
        <KEYEVENT>
          <ID>6</ID>
          <KIND>branch</KIND>
          <IMPORTANCE>Full</IMPORTANCE>
          <MESSAGE>Enter this branch, (assume '&lt;branch condition&gt;')</MESSAGE>
        </KEYEVENT>
      </SFA>
      <SFA>
        <FILEPATH>E:\XBLAH\content\Mapbase\klepto\src\game\server\</FILEPATH>
        <FILENAME>BaseAnimatingOverlay.cpp</FILENAME>
        <LINE>258</LINE>
        <COLUMN>5</COLUMN>
      </SFA>
      <SFA>
        <FILEPATH>E:\XBLAH\content\Mapbase\klepto\src\game\server\</FILEPATH>
        <FILENAME>BaseAnimatingOverlay.cpp</FILENAME>
        <LINE>259</LINE>
        <COLUMN>3</COLUMN>
      </SFA>
      <SFA>
        <FILEPATH>E:\XBLAH\content\Mapbase\klepto\src\game\server\</FILEPATH>
        <FILENAME>BaseAnimatingOverlay.cpp</FILENAME>
        <LINE>260</LINE>
        <COLUMN>12</COLUMN>
        <KEYEVENT>
          <ID>7</ID>
          <KIND>usage</KIND>
          <IMPORTANCE>Essential</IMPORTANCE>
          <MESSAGE>Invalid write to 'layer[-1]', (writable range is 0 to 14)</MESSAGE>
        </KEYEVENT>
      </SFA>
    </PATH>
  </DEFECT>
</DEFECTS>