<?xml version="1.0" encoding="UTF-8"?>
<DEFECTS>
  <DEFECT>
    <SFA>
      <FILEPATH>E:\XBLAH\content\Mapbase\klepto\src\public\mathlib\</FILEPATH>
      <FILENAME>ssemath.h</FILENAME>
      <LINE>2583</LINE>
      <COLUMN>1</COLUMN>
    </SFA>
    <DEFECTCODE>26495</DEFECTCODE>
    <DESCRIPTION>Variable 'FourVectors::z' is uninitialized. Always initialize a member variable (type.6).</DESCRIPTION>
    <FUNCTION>FourVectors::{ctor}</FUNCTION>
    <DECORATED>??0FourVectors@@QAE@XZ</DECORATED>
    <FUNCLINE>2583</FUNCLINE>
    <ADDITIONALINFO>
      <targetSymbol>FourVectors::z</targetSymbol>
    </ADDITIONALINFO>
    <PATH></PATH>
  </DEFECT>
  <DEFECT>
    <SFA>
      <FILEPATH>E:\XBLAH\content\Mapbase\klepto\src\public\mathlib\</FILEPATH>
      <FILENAME>ssemath.h</FILENAME>
      <LINE>2583</LINE>
      <COLUMN>1</COLUMN>
    </SFA>
    <DEFECTCODE>26495</DEFECTCODE>
    <DESCRIPTION>Variable 'FourVectors::y' is uninitialized. Always initialize a member variable (type.6).</DESCRIPTION>
    <FUNCTION>FourVectors::{ctor}</FUNCTION>
    <DECORATED>??0FourVectors@@QAE@XZ</DECORATED>
    <FUNCLINE>2583</FUNCLINE>
    <ADDITIONALINFO>
      <targetSymbol>FourVectors::y</targetSymbol>
    </ADDITIONALINFO>
    <PATH></PATH>
  </DEFECT>
  <DEFECT>
    <SFA>
      <FILEPATH>E:\XBLAH\content\Mapbase\klepto\src\public\mathlib\</FILEPATH>
      <FILENAME>ssemath.h</FILENAME>
      <LINE>2583</LINE>
      <COLUMN>1</COLUMN>
    </SFA>
    <DEFECTCODE>26495</DEFECTCODE>
    <DESCRIPTION>Variable 'FourVectors::x' is uninitialized. Always initialize a member variable (type.6).</DESCRIPTION>
    <FUNCTION>FourVectors::{ctor}</FUNCTION>
    <DECORATED>??0FourVectors@@QAE@XZ</DECORATED>
    <FUNCLINE>2583</FUNCLINE>
    <ADDITIONALINFO>
      <targetSymbol>FourVectors::x</targetSymbol>
    </ADDITIONALINFO>
    <PATH></PATH>
  </DEFECT>
  <DEFECT>
    <SFA>
      <FILEPATH>E:\XBLAH\content\Mapbase\klepto\src\public\</FILEPATH>
      <FILENAME>bone_setup.h</FILENAME>
      <LINE>252</LINE>
      <COLUMN>1</COLUMN>
    </SFA>
    <DEFECTCODE>26495</DEFECTCODE>
    <DESCRIPTION>Variable 'ikcontextikrule_t::height' is uninitialized. Always initialize a member variable (type.6).</DESCRIPTION>
    <FUNCTION>ikcontextikrule_t::{ctor}</FUNCTION>
    <DECORATED>??0ikcontextikrule_t@@QAE@XZ</DECORATED>
    <FUNCLINE>252</FUNCLINE>
    <ADDITIONALINFO>
      <targetSymbol>ikcontextikrule_t::height</targetSymbol>
    </ADDITIONALINFO>
    <PATH></PATH>
  </DEFECT>
  <DEFECT>
    <SFA>
      <FILEPATH>E:\XBLAH\content\Mapbase\klepto\src\public\</FILEPATH>
      <FILENAME>bone_setup.h</FILENAME>
      <LINE>252</LINE>
      <COLUMN>1</COLUMN>
    </SFA>
    <DEFECTCODE>26495</DEFECTCODE>
    <DESCRIPTION>Variable 'ikcontextikrule_t::floor' is uninitialized. Always initialize a member variable (type.6).</DESCRIPTION>
    <FUNCTION>ikcontextikrule_t::{ctor}</FUNCTION>
    <DECORATED>??0ikcontextikrule_t@@QAE@XZ</DECORATED>
    <FUNCLINE>252</FUNCLINE>
    <ADDITIONALINFO>
      <targetSymbol>ikcontextikrule_t::floor</targetSymbol>
    </ADDITIONALINFO>
    <PATH></PATH>
  </DEFECT>
  <DEFECT>
    <SFA>
      <FILEPATH>E:\XBLAH\content\Mapbase\klepto\src\public\</FILEPATH>
      <FILENAME>bone_setup.h</FILENAME>
      <LINE>252</LINE>
      <COLUMN>1</COLUMN>
    </SFA>
    <DEFECTCODE>26495</DEFECTCODE>
    <DESCRIPTION>Variable 'ikcontextikrule_t::flWeight' is uninitialized. Always initialize a member variable (type.6).</DESCRIPTION>
    <FUNCTION>ikcontextikrule_t::{ctor}</FUNCTION>
    <DECORATED>??0ikcontextikrule_t@@QAE@XZ</DECORATED>
    <FUNCLINE>252</FUNCLINE>
    <ADDITIONALINFO>
      <targetSymbol>ikcontextikrule_t::flWeight</targetSymbol>
    </ADDITIONALINFO>
    <PATH></PATH>
  </DEFECT>
  <DEFECT>
    <SFA>
      <FILEPATH>E:\XBLAH\content\Mapbase\klepto\src\public\</FILEPATH>
      <FILENAME>bone_setup.h</FILENAME>
      <LINE>252</LINE>
      <COLUMN>1</COLUMN>
    </SFA>
    <DEFECTCODE>26495</DEFECTCODE>
    <DESCRIPTION>Variable 'ikcontextikrule_t::commit' is uninitialized. Always initialize a member variable (type.6).</DESCRIPTION>
    <FUNCTION>ikcontextikrule_t::{ctor}</FUNCTION>
    <DECORATED>??0ikcontextikrule_t@@QAE@XZ</DECORATED>
    <FUNCLINE>252</FUNCLINE>
    <ADDITIONALINFO>
      <targetSymbol>ikcontextikrule_t::commit</targetSymbol>
    </ADDITIONALINFO>
    <PATH></PATH>
  </DEFECT>
  <DEFECT>
    <SFA>
      <FILEPATH>E:\XBLAH\content\Mapbase\klepto\src\public\</FILEPATH>
      <FILENAME>bone_setup.h</FILENAME>
      <LINE>252</LINE>
      <COLUMN>1</COLUMN>
    </SFA>
    <DEFECTCODE>26495</DEFECTCODE>
    <DESCRIPTION>Variable 'ikcontextikrule_t::drop' is uninitialized. Always initialize a member variable (type.6).</DESCRIPTION>
    <FUNCTION>ikcontextikrule_t::{ctor}</FUNCTION>
    <DECORATED>??0ikcontextikrule_t@@QAE@XZ</DECORATED>
    <FUNCLINE>252</FUNCLINE>
    <ADDITIONALINFO>
      <targetSymbol>ikcontextikrule_t::drop</targetSymbol>
    </ADDITIONALINFO>
    <PATH></PATH>
  </DEFECT>
  <DEFECT>
    <SFA>
      <FILEPATH>E:\XBLAH\content\Mapbase\klepto\src\public\</FILEPATH>
      <FILENAME>bone_setup.h</FILENAME>
      <LINE>252</LINE>
      <COLUMN>1</COLUMN>
    </SFA>
    <DEFECTCODE>26495</DEFECTCODE>
    <DESCRIPTION>Variable 'ikcontextikrule_t::szLabel' is uninitialized. Always initialize a member variable (type.6).</DESCRIPTION>
    <FUNCTION>ikcontextikrule_t::{ctor}</FUNCTION>
    <DECORATED>??0ikcontextikrule_t@@QAE@XZ</DECORATED>
    <FUNCLINE>252</FUNCLINE>
    <ADDITIONALINFO>
      <targetSymbol>ikcontextikrule_t::szLabel</targetSymbol>
    </ADDITIONALINFO>
    <PATH></PATH>
  </DEFECT>
  <DEFECT>
    <SFA>
      <FILEPATH>E:\XBLAH\content\Mapbase\klepto\src\public\</FILEPATH>
      <FILENAME>bone_setup.h</FILENAME>
      <LINE>252</LINE>
      <COLUMN>1</COLUMN>
    </SFA>
    <DEFECTCODE>26495</DEFECTCODE>
    <DESCRIPTION>Variable 'ikcontextikrule_t::slot' is uninitialized. Always initialize a member variable (type.6).</DESCRIPTION>
    <FUNCTION>ikcontextikrule_t::{ctor}</FUNCTION>
    <DECORATED>??0ikcontextikrule_t@@QAE@XZ</DECORATED>
    <FUNCLINE>252</FUNCLINE>
    <ADDITIONALINFO>
      <targetSymbol>ikcontextikrule_t::slot</targetSymbol>
    </ADDITIONALINFO>
    <PATH></PATH>
  </DEFECT>
  <DEFECT>
    <SFA>
      <FILEPATH>E:\XBLAH\content\Mapbase\klepto\src\public\</FILEPATH>
      <FILENAME>bone_setup.h</FILENAME>
      <LINE>252</LINE>
      <COLUMN>1</COLUMN>
    </SFA>
    <DEFECTCODE>26495</DEFECTCODE>
    <DESCRIPTION>Variable 'ikcontextikrule_t::bone' is uninitialized. Always initialize a member variable (type.6).</DESCRIPTION>
    <FUNCTION>ikcontextikrule_t::{ctor}</FUNCTION>
    <DECORATED>??0ikcontextikrule_t@@QAE@XZ</DECORATED>
    <FUNCLINE>252</FUNCLINE>
    <ADDITIONALINFO>
      <targetSymbol>ikcontextikrule_t::bone</targetSymbol>
    </ADDITIONALINFO>
    <PATH></PATH>
  </DEFECT>
  <DEFECT>
    <SFA>
      <FILEPATH>E:\XBLAH\content\Mapbase\klepto\src\public\</FILEPATH>
      <FILENAME>bone_setup.h</FILENAME>
      <LINE>252</LINE>
      <COLUMN>1</COLUMN>
    </SFA>
    <DEFECTCODE>26495</DEFECTCODE>
    <DESCRIPTION>Variable 'ikcontextikrule_t::release' is uninitialized. Always initialize a member variable (type.6).</DESCRIPTION>
    <FUNCTION>ikcontextikrule_t::{ctor}</FUNCTION>
    <DECORATED>??0ikcontextikrule_t@@QAE@XZ</DECORATED>
    <FUNCLINE>252</FUNCLINE>
    <ADDITIONALINFO>
      <targetSymbol>ikcontextikrule_t::release</targetSymbol>
    </ADDITIONALINFO>
    <PATH></PATH>
  </DEFECT>
  <DEFECT>
    <SFA>
      <FILEPATH>E:\XBLAH\content\Mapbase\klepto\src\public\</FILEPATH>
      <FILENAME>bone_setup.h</FILENAME>
      <LINE>252</LINE>
      <COLUMN>1</COLUMN>
    </SFA>
    <DEFECTCODE>26495</DEFECTCODE>
    <DESCRIPTION>Variable 'ikcontextikrule_t::top' is uninitialized. Always initialize a member variable (type.6).</DESCRIPTION>
    <FUNCTION>ikcontextikrule_t::{ctor}</FUNCTION>
    <DECORATED>??0ikcontextikrule_t@@QAE@XZ</DECORATED>
    <FUNCLINE>252</FUNCLINE>
    <ADDITIONALINFO>
      <targetSymbol>ikcontextikrule_t::top</targetSymbol>
    </ADDITIONALINFO>
    <PATH></PATH>
  </DEFECT>
  <DEFECT>
    <SFA>
      <FILEPATH>E:\XBLAH\content\Mapbase\klepto\src\public\</FILEPATH>
      <FILENAME>bone_setup.h</FILENAME>
      <LINE>252</LINE>
      <COLUMN>1</COLUMN>
    </SFA>
    <DEFECTCODE>26495</DEFECTCODE>
    <DESCRIPTION>Variable 'ikcontextikrule_t::peak' is uninitialized. Always initialize a member variable (type.6).</DESCRIPTION>
    <FUNCTION>ikcontextikrule_t::{ctor}</FUNCTION>
    <DECORATED>??0ikcontextikrule_t@@QAE@XZ</DECORATED>
    <FUNCLINE>252</FUNCLINE>
    <ADDITIONALINFO>
      <targetSymbol>ikcontextikrule_t::peak</targetSymbol>
    </ADDITIONALINFO>
    <PATH></PATH>
  </DEFECT>
  <DEFECT>
    <SFA>
      <FILEPATH>E:\XBLAH\content\Mapbase\klepto\src\public\</FILEPATH>
      <FILENAME>bone_setup.h</FILENAME>
      <LINE>252</LINE>
      <COLUMN>1</COLUMN>
    </SFA>
    <DEFECTCODE>26495</DEFECTCODE>
    <DESCRIPTION>Variable 'ikcontextikrule_t::index' is uninitialized. Always initialize a member variable (type.6).</DESCRIPTION>
    <FUNCTION>ikcontextikrule_t::{ctor}</FUNCTION>
    <DECORATED>??0ikcontextikrule_t@@QAE@XZ</DECORATED>
    <FUNCLINE>252</FUNCLINE>
    <ADDITIONALINFO>
      <targetSymbol>ikcontextikrule_t::index</targetSymbol>
    </ADDITIONALINFO>
    <PATH></PATH>
  </DEFECT>
  <DEFECT>
    <SFA>
      <FILEPATH>E:\XBLAH\content\Mapbase\klepto\src\public\</FILEPATH>
      <FILENAME>bone_setup.h</FILENAME>
      <LINE>252</LINE>
      <COLUMN>1</COLUMN>
    </SFA>
    <DEFECTCODE>26495</DEFECTCODE>
    <DESCRIPTION>Variable 'ikcontextikrule_t::type' is uninitialized. Always initialize a member variable (type.6).</DESCRIPTION>
    <FUNCTION>ikcontextikrule_t::{ctor}</FUNCTION>
    <DECORATED>??0ikcontextikrule_t@@QAE@XZ</DECORATED>
    <FUNCLINE>252</FUNCLINE>
    <ADDITIONALINFO>
      <targetSymbol>ikcontextikrule_t::type</targetSymbol>
    </ADDITIONALINFO>
    <PATH></PATH>
  </DEFECT>
  <DEFECT>
    <SFA>
      <FILEPATH>E:\XBLAH\content\Mapbase\klepto\src\public\</FILEPATH>
      <FILENAME>bone_setup.h</FILENAME>
      <LINE>252</LINE>
      <COLUMN>1</COLUMN>
    </SFA>
    <DEFECTCODE>26495</DEFECTCODE>
    <DESCRIPTION>Variable 'ikcontextikrule_t::start' is uninitialized. Always initialize a member variable (type.6).</DESCRIPTION>
    <FUNCTION>ikcontextikrule_t::{ctor}</FUNCTION>
    <DECORATED>??0ikcontextikrule_t@@QAE@XZ</DECORATED>
    <FUNCLINE>252</FUNCLINE>
    <ADDITIONALINFO>
      <targetSymbol>ikcontextikrule_t::start</targetSymbol>
    </ADDITIONALINFO>
    <PATH></PATH>
  </DEFECT>
  <DEFECT>
    <SFA>
      <FILEPATH>E:\XBLAH\content\Mapbase\klepto\src\public\</FILEPATH>
      <FILENAME>bone_setup.h</FILENAME>
      <LINE>252</LINE>
      <COLUMN>1</COLUMN>
    </SFA>
    <DEFECTCODE>26495</DEFECTCODE>
    <DESCRIPTION>Variable 'ikcontextikrule_t::flRuleWeight' is uninitialized. Always initialize a member variable (type.6).</DESCRIPTION>
    <FUNCTION>ikcontextikrule_t::{ctor}</FUNCTION>
    <DECORATED>??0ikcontextikrule_t@@QAE@XZ</DECORATED>
    <FUNCLINE>252</FUNCLINE>
    <ADDITIONALINFO>
      <targetSymbol>ikcontextikrule_t::flRuleWeight</targetSymbol>
    </ADDITIONALINFO>
    <PATH></PATH>
  </DEFECT>
  <DEFECT>
    <SFA>
      <FILEPATH>E:\XBLAH\content\Mapbase\klepto\src\public\</FILEPATH>
      <FILENAME>bone_setup.h</FILENAME>
      <LINE>252</LINE>
      <COLUMN>1</COLUMN>
    </SFA>
    <DEFECTCODE>26495</DEFECTCODE>
    <DESCRIPTION>Variable 'ikcontextikrule_t::latched' is uninitialized. Always initialize a member variable (type.6).</DESCRIPTION>
    <FUNCTION>ikcontextikrule_t::{ctor}</FUNCTION>
    <DECORATED>??0ikcontextikrule_t@@QAE@XZ</DECORATED>
    <FUNCLINE>252</FUNCLINE>
    <ADDITIONALINFO>
      <targetSymbol>ikcontextikrule_t::latched</targetSymbol>
    </ADDITIONALINFO>
    <PATH></PATH>
  </DEFECT>
  <DEFECT>
    <SFA>
      <FILEPATH>E:\XBLAH\content\Mapbase\klepto\src\public\</FILEPATH>
      <FILENAME>bone_setup.h</FILENAME>
      <LINE>252</LINE>
      <COLUMN>1</COLUMN>
    </SFA>
    <DEFECTCODE>26495</DEFECTCODE>
    <DESCRIPTION>Variable 'ikcontextikrule_t::tail' is uninitialized. Always initialize a member variable (type.6).</DESCRIPTION>
    <FUNCTION>ikcontextikrule_t::{ctor}</FUNCTION>
    <DECORATED>??0ikcontextikrule_t@@QAE@XZ</DECORATED>
    <FUNCLINE>252</FUNCLINE>
    <ADDITIONALINFO>
      <targetSymbol>ikcontextikrule_t::tail</targetSymbol>
    </ADDITIONALINFO>
    <PATH></PATH>
  </DEFECT>
  <DEFECT>
    <SFA>
      <FILEPATH>E:\XBLAH\content\Mapbase\klepto\src\public\</FILEPATH>
      <FILENAME>bone_setup.h</FILENAME>
      <LINE>252</LINE>
      <COLUMN>1</COLUMN>
    </SFA>
    <DEFECTCODE>26495</DEFECTCODE>
    <DESCRIPTION>Variable 'ikcontextikrule_t::chain' is uninitialized. Always initialize a member variable (type.6).</DESCRIPTION>
    <FUNCTION>ikcontextikrule_t::{ctor}</FUNCTION>
    <DECORATED>??0ikcontextikrule_t@@QAE@XZ</DECORATED>
    <FUNCLINE>252</FUNCLINE>
    <ADDITIONALINFO>
      <targetSymbol>ikcontextikrule_t::chain</targetSymbol>
    </ADDITIONALINFO>
    <PATH></PATH>
  </DEFECT>
  <DEFECT>
    <SFA>
      <FILEPATH>E:\XBLAH\content\Mapbase\klepto\src\public\</FILEPATH>
      <FILENAME>bone_setup.h</FILENAME>
      <LINE>252</LINE>
      <COLUMN>1</COLUMN>
    </SFA>
    <DEFECTCODE>26495</DEFECTCODE>
    <DESCRIPTION>Variable 'ikcontextikrule_t::radius' is uninitialized. Always initialize a member variable (type.6).</DESCRIPTION>
    <FUNCTION>ikcontextikrule_t::{ctor}</FUNCTION>
    <DECORATED>??0ikcontextikrule_t@@QAE@XZ</DECORATED>
    <FUNCLINE>252</FUNCLINE>
    <ADDITIONALINFO>
      <targetSymbol>ikcontextikrule_t::radius</targetSymbol>
    </ADDITIONALINFO>
    <PATH></PATH>
  </DEFECT>
  <DEFECT>
    <SFA>
      <FILEPATH>E:\XBLAH\content\Mapbase\klepto\src\public\</FILEPATH>
      <FILENAME>bone_setup.h</FILENAME>
      <LINE>252</LINE>
      <COLUMN>1</COLUMN>
    </SFA>
    <DEFECTCODE>26495</DEFECTCODE>
    <DESCRIPTION>Variable 'ikcontextikrule_t::end' is uninitialized. Always initialize a member variable (type.6).</DESCRIPTION>
    <FUNCTION>ikcontextikrule_t::{ctor}</FUNCTION>
    <DECORATED>??0ikcontextikrule_t@@QAE@XZ</DECORATED>
    <FUNCLINE>252</FUNCLINE>
    <ADDITIONALINFO>
      <targetSymbol>ikcontextikrule_t::end</targetSymbol>
    </ADDITIONALINFO>
    <PATH></PATH>
  </DEFECT>
  <DEFECT>
    <SFA>
      <FILEPATH>E:\XBLAH\content\Mapbase\klepto\src\public\</FILEPATH>
      <FILENAME>vcollide_parse.h</FILENAME>
      <LINE>33</LINE>
      <COLUMN>1</COLUMN>
    </SFA>
    <DEFECTCODE>26495</DEFECTCODE>
    <DESCRIPTION>Variable 'fluid_t::surfaceprop' is uninitialized. Always initialize a member variable (type.6).</DESCRIPTION>
    <FUNCTION>fluid_t::{ctor}</FUNCTION>
    <DECORATED>??0fluid_t@@QAE@XZ</DECORATED>
    <FUNCLINE>33</FUNCLINE>
    <ADDITIONALINFO>
      <targetSymbol>fluid_t::surfaceprop</targetSymbol>
    </ADDITIONALINFO>
    <PATH></PATH>
  </DEFECT>
  <DEFECT>
    <SFA>
      <FILEPATH>E:\XBLAH\content\Mapbase\klepto\src\public\</FILEPATH>
      <FILENAME>vcollide_parse.h</FILENAME>
      <LINE>33</LINE>
      <COLUMN>1</COLUMN>
    </SFA>
    <DEFECTCODE>26495</DEFECTCODE>
    <DESCRIPTION>Variable 'fluid_t::index' is uninitialized. Always initialize a member variable (type.6).</DESCRIPTION>
    <FUNCTION>fluid_t::{ctor}</FUNCTION>
    <DECORATED>??0fluid_t@@QAE@XZ</DECORATED>
    <FUNCLINE>33</FUNCLINE>
    <ADDITIONALINFO>
      <targetSymbol>fluid_t::index</targetSymbol>
    </ADDITIONALINFO>
    <PATH></PATH>
  </DEFECT>
  <DEFECT>
    <SFA>
      <FILEPATH>E:\XBLAH\content\Mapbase\klepto\src\public\</FILEPATH>
      <FILENAME>vcollide_parse.h</FILENAME>
      <LINE>34</LINE>
      <COLUMN>1</COLUMN>
    </SFA>
    <DEFECTCODE>26495</DEFECTCODE>
    <DESCRIPTION>Variable 'fluid_t::surfaceprop' is uninitialized. Always initialize a member variable (type.6).</DESCRIPTION>
    <FUNCTION>fluid_t::{ctor}</FUNCTION>
    <DECORATED>??0fluid_t@@QAE@ABU0@@Z</DECORATED>
    <FUNCLINE>34</FUNCLINE>
    <ADDITIONALINFO>
      <targetSymbol>fluid_t::surfaceprop</targetSymbol>
    </ADDITIONALINFO>
    <PATH></PATH>
  </DEFECT>
  <DEFECT>
    <SFA>
      <FILEPATH>E:\XBLAH\content\Mapbase\klepto\src\game\server\</FILEPATH>
      <FILENAME>filters.h</FILENAME>
      <LINE>107</LINE>
      <COLUMN>1</COLUMN>
    </SFA>
    <DEFECTCODE>26495</DEFECTCODE>
    <DESCRIPTION>Variable 'CTraceFilterEntityFilter::m_bHitIfPassed' is uninitialized. Always initialize a member variable (type.6).</DESCRIPTION>
    <FUNCTION>CTraceFilterEntityFilter::{ctor}</FUNCTION>
    <DECORATED>??0CTraceFilterEntityFilter@@QAE@PBVIHandleEntity@@H@Z</DECORATED>
    <FUNCLINE>107</FUNCLINE>
    <ADDITIONALINFO>
      <targetSymbol>CTraceFilterEntityFilter::m_bHitIfPassed</targetSymbol>
    </ADDITIONALINFO>
    <PATH></PATH>
  </DEFECT>
  <DEFECT>
    <SFA>
      <FILEPATH>E:\XBLAH\content\Mapbase\klepto\src\game\server\</FILEPATH>
      <FILENAME>filters.h</FILENAME>
      <LINE>107</LINE>
      <COLUMN>1</COLUMN>
    </SFA>
    <DEFECTCODE>26495</DEFECTCODE>
    <DESCRIPTION>Variable 'CTraceFilterEntityFilter::m_pFilter' is uninitialized. Always initialize a member variable (type.6).</DESCRIPTION>
    <FUNCTION>CTraceFilterEntityFilter::{ctor}</FUNCTION>
    <DECORATED>??0CTraceFilterEntityFilter@@QAE@PBVIHandleEntity@@H@Z</DECORATED>
    <FUNCLINE>107</FUNCLINE>
    <ADDITIONALINFO>
      <targetSymbol>CTraceFilterEntityFilter::m_pFilter</targetSymbol>
    </ADDITIONALINFO>
    <PATH></PATH>
  </DEFECT>
  <DEFECT>
    <SFA>
      <FILEPATH>E:\XBLAH\content\Mapbase\klepto\src\game\server\</FILEPATH>
      <FILENAME>filters.h</FILENAME>
      <LINE>107</LINE>
      <COLUMN>1</COLUMN>
    </SFA>
    <DEFECTCODE>26495</DEFECTCODE>
    <DESCRIPTION>Variable 'CTraceFilterEntityFilter::m_bFilterExclusive' is uninitialized. Always initialize a member variable (type.6).</DESCRIPTION>
    <FUNCTION>CTraceFilterEntityFilter::{ctor}</FUNCTION>
    <DECORATED>??0CTraceFilterEntityFilter@@QAE@PBVIHandleEntity@@H@Z</DECORATED>
    <FUNCLINE>107</FUNCLINE>
    <ADDITIONALINFO>
      <targetSymbol>CTraceFilterEntityFilter::m_bFilterExclusive</targetSymbol>
    </ADDITIONALINFO>
    <PATH></PATH>
  </DEFECT>
  <DEFECT>
    <SFA>
      <FILEPATH>E:\XBLAH\content\Mapbase\klepto\src\game\server\</FILEPATH>
      <FILENAME>filters.h</FILENAME>
      <LINE>107</LINE>
      <COLUMN>1</COLUMN>
    </SFA>
    <DEFECTCODE>26495</DEFECTCODE>
    <DESCRIPTION>Variable 'CTraceFilterEntityFilter::m_pCaller' is uninitialized. Always initialize a member variable (type.6).</DESCRIPTION>
    <FUNCTION>CTraceFilterEntityFilter::{ctor}</FUNCTION>
    <DECORATED>??0CTraceFilterEntityFilter@@QAE@PBVIHandleEntity@@H@Z</DECORATED>
    <FUNCLINE>107</FUNCLINE>
    <ADDITIONALINFO>
      <targetSymbol>CTraceFilterEntityFilter::m_pCaller</targetSymbol>
    </ADDITIONALINFO>
    <PATH></PATH>
  </DEFECT>
  <DEFECT>
    <SFA>
      <FILEPATH>E:\XBLAH\content\Mapbase\klepto\src\game\server\</FILEPATH>
      <FILENAME>filters.h</FILENAME>
      <LINE>108</LINE>
      <COLUMN>1</COLUMN>
    </SFA>
    <DEFECTCODE>26495</DEFECTCODE>
    <DESCRIPTION>Variable 'CTraceFilterEntityFilter::m_bHitIfPassed' is uninitialized. Always initialize a member variable (type.6).</DESCRIPTION>
    <FUNCTION>CTraceFilterEntityFilter::{ctor}</FUNCTION>
    <DECORATED>??0CTraceFilterEntityFilter@@QAE@H@Z</DECORATED>
    <FUNCLINE>108</FUNCLINE>
    <ADDITIONALINFO>
      <targetSymbol>CTraceFilterEntityFilter::m_bHitIfPassed</targetSymbol>
    </ADDITIONALINFO>
    <PATH></PATH>
  </DEFECT>
  <DEFECT>
    <SFA>
      <FILEPATH>E:\XBLAH\content\Mapbase\klepto\src\game\server\</FILEPATH>
      <FILENAME>filters.h</FILENAME>
      <LINE>108</LINE>
      <COLUMN>1</COLUMN>
    </SFA>
    <DEFECTCODE>26495</DEFECTCODE>
    <DESCRIPTION>Variable 'CTraceFilterEntityFilter::m_pFilter' is uninitialized. Always initialize a member variable (type.6).</DESCRIPTION>
    <FUNCTION>CTraceFilterEntityFilter::{ctor}</FUNCTION>
    <DECORATED>??0CTraceFilterEntityFilter@@QAE@H@Z</DECORATED>
    <FUNCLINE>108</FUNCLINE>
    <ADDITIONALINFO>
      <targetSymbol>CTraceFilterEntityFilter::m_pFilter</targetSymbol>
    </ADDITIONALINFO>
    <PATH></PATH>
  </DEFECT>
  <DEFECT>
    <SFA>
      <FILEPATH>E:\XBLAH\content\Mapbase\klepto\src\game\server\</FILEPATH>
      <FILENAME>filters.h</FILENAME>
      <LINE>108</LINE>
      <COLUMN>1</COLUMN>
    </SFA>
    <DEFECTCODE>26495</DEFECTCODE>
    <DESCRIPTION>Variable 'CTraceFilterEntityFilter::m_bFilterExclusive' is uninitialized. Always initialize a member variable (type.6).</DESCRIPTION>
    <FUNCTION>CTraceFilterEntityFilter::{ctor}</FUNCTION>
    <DECORATED>??0CTraceFilterEntityFilter@@QAE@H@Z</DECORATED>
    <FUNCLINE>108</FUNCLINE>
    <ADDITIONALINFO>
      <targetSymbol>CTraceFilterEntityFilter::m_bFilterExclusive</targetSymbol>
    </ADDITIONALINFO>
    <PATH></PATH>
  </DEFECT>
  <DEFECT>
    <SFA>
      <FILEPATH>E:\XBLAH\content\Mapbase\klepto\src\game\server\</FILEPATH>
      <FILENAME>filters.h</FILENAME>
      <LINE>108</LINE>
      <COLUMN>1</COLUMN>
    </SFA>
    <DEFECTCODE>26495</DEFECTCODE>
    <DESCRIPTION>Variable 'CTraceFilterEntityFilter::m_pCaller' is uninitialized. Always initialize a member variable (type.6).</DESCRIPTION>
    <FUNCTION>CTraceFilterEntityFilter::{ctor}</FUNCTION>
    <DECORATED>??0CTraceFilterEntityFilter@@QAE@H@Z</DECORATED>
    <FUNCLINE>108</FUNCLINE>
    <ADDITIONALINFO>
      <targetSymbol>CTraceFilterEntityFilter::m_pCaller</targetSymbol>
    </ADDITIONALINFO>
    <PATH></PATH>
  </DEFECT>
  <DEFECT>
    <SFA>
      <FILEPATH>E:\XBLAH\content\Mapbase\klepto\src\game\shared\</FILEPATH>
      <FILENAME>effect_dispatch_data.h</FILENAME>
      <LINE>76</LINE>
      <COLUMN>1</COLUMN>
    </SFA>
    <DEFECTCODE>26495</DEFECTCODE>
    <DESCRIPTION>Variable 'CEffectData::m_iEffectName' is uninitialized. Always initialize a member variable (type.6).</DESCRIPTION>
    <FUNCTION>CEffectData::{ctor}</FUNCTION>
    <DECORATED>??0CEffectData@@QAE@XZ</DECORATED>
    <FUNCLINE>76</FUNCLINE>
    <ADDITIONALINFO>
      <targetSymbol>CEffectData::m_iEffectName</targetSymbol>
    </ADDITIONALINFO>
    <PATH></PATH>
  </DEFECT>
  <DEFECT>
    <SFA>
      <FILEPATH>E:\XBLAH\content\Mapbase\klepto\src\game\shared\</FILEPATH>
      <FILENAME>particle_parse.h</FILENAME>
      <LINE>50</LINE>
      <COLUMN>0</COLUMN>
    </SFA>
    <DEFECTCODE>26495</DEFECTCODE>
    <DESCRIPTION>Variable 'te_tf_particle_effects_control_point_t::m_eParticleAttachment' is uninitialized. Always initialize a member variable (type.6).</DESCRIPTION>
    <FUNCTION>te_tf_particle_effects_control_point_t::{ctor}</FUNCTION>
    <DECORATED>??0te_tf_particle_effects_control_point_t@@QAE@XZ</DECORATED>
    <FUNCLINE>50</FUNCLINE>
    <ADDITIONALINFO>
      <targetSymbol>te_tf_particle_effects_control_point_t::m_eParticleAttachment</targetSymbol>
    </ADDITIONALINFO>
    <PATH></PATH>
  </DEFECT>
  <DEFECT>
    <SFA>
      <FILEPATH>E:\XBLAH\content\Mapbase\klepto\src\public\</FILEPATH>
      <FILENAME>saverestoretypes.h</FILENAME>
      <LINE>283</LINE>
      <COLUMN>2</COLUMN>
    </SFA>
    <DEFECTCODE>26495</DEFECTCODE>
    <DESCRIPTION>Variable 'CGameSaveRestoreInfo::CHashElement::index' is uninitialized. Always initialize a member variable (type.6).</DESCRIPTION>
    <FUNCTION>CGameSaveRestoreInfo::CHashElement::{ctor}</FUNCTION>
    <DECORATED>??0CHashElement@CGameSaveRestoreInfo@@QAE@PBVCBaseEntity@@@Z</DECORATED>
    <FUNCLINE>283</FUNCLINE>
    <ADDITIONALINFO>
      <targetSymbol>CGameSaveRestoreInfo::CHashElement::index</targetSymbol>
    </ADDITIONALINFO>
    <PATH></PATH>
  </DEFECT>
  <DEFECT>
    <SFA>
      <FILEPATH>E:\XBLAH\content\Mapbase\klepto\src\public\</FILEPATH>
      <FILENAME>saverestoretypes.h</FILENAME>
      <LINE>284</LINE>
      <COLUMN>2</COLUMN>
    </SFA>
    <DEFECTCODE>26495</DEFECTCODE>
    <DESCRIPTION>Variable 'CGameSaveRestoreInfo::CHashElement::pEntity' is uninitialized. Always initialize a member variable (type.6).</DESCRIPTION>
    <FUNCTION>CGameSaveRestoreInfo::CHashElement::{ctor}</FUNCTION>
    <DECORATED>??0CHashElement@CGameSaveRestoreInfo@@QAE@XZ</DECORATED>
    <FUNCLINE>284</FUNCLINE>
    <ADDITIONALINFO>
      <targetSymbol>CGameSaveRestoreInfo::CHashElement::pEntity</targetSymbol>
    </ADDITIONALINFO>
    <PATH></PATH>
  </DEFECT>
  <DEFECT>
    <SFA>
      <FILEPATH>E:\XBLAH\content\Mapbase\klepto\src\public\</FILEPATH>
      <FILENAME>saverestoretypes.h</FILENAME>
      <LINE>284</LINE>
      <COLUMN>2</COLUMN>
    </SFA>
    <DEFECTCODE>26495</DEFECTCODE>
    <DESCRIPTION>Variable 'CGameSaveRestoreInfo::CHashElement::index' is uninitialized. Always initialize a member variable (type.6).</DESCRIPTION>
    <FUNCTION>CGameSaveRestoreInfo::CHashElement::{ctor}</FUNCTION>
    <DECORATED>??0CHashElement@CGameSaveRestoreInfo@@QAE@XZ</DECORATED>
    <FUNCLINE>284</FUNCLINE>
    <ADDITIONALINFO>
      <targetSymbol>CGameSaveRestoreInfo::CHashElement::index</targetSymbol>
    </ADDITIONALINFO>
    <PATH></PATH>
  </DEFECT>
  <DEFECT>
    <SFA>
      <FILEPATH>E:\XBLAH\content\Mapbase\klepto\src\public\</FILEPATH>
      <FILENAME>saverestoretypes.h</FILENAME>
      <LINE>176</LINE>
      <COLUMN>0</COLUMN>
    </SFA>
    <DEFECTCODE>26495</DEFECTCODE>
    <DESCRIPTION>Variable 'saverestorelevelinfo_t::mapVersion' is uninitialized. Always initialize a member variable (type.6).</DESCRIPTION>
    <FUNCTION>saverestorelevelinfo_t::{ctor}</FUNCTION>
    <DECORATED>??0saverestorelevelinfo_t@@QAE@XZ</DECORATED>
    <FUNCLINE>176</FUNCLINE>
    <ADDITIONALINFO>
      <targetSymbol>saverestorelevelinfo_t::mapVersion</targetSymbol>
    </ADDITIONALINFO>
    <PATH></PATH>
  </DEFECT>
  <DEFECT>
    <SFA>
      <FILEPATH>E:\XBLAH\content\Mapbase\klepto\src\public\</FILEPATH>
      <FILENAME>saverestoretypes.h</FILENAME>
      <LINE>176</LINE>
      <COLUMN>0</COLUMN>
    </SFA>
    <DEFECTCODE>26495</DEFECTCODE>
    <DESCRIPTION>Variable 'saverestorelevelinfo_t::connectionCount' is uninitialized. Always initialize a member variable (type.6).</DESCRIPTION>
    <FUNCTION>saverestorelevelinfo_t::{ctor}</FUNCTION>
    <DECORATED>??0saverestorelevelinfo_t@@QAE@XZ</DECORATED>
    <FUNCLINE>176</FUNCLINE>
    <ADDITIONALINFO>
      <targetSymbol>saverestorelevelinfo_t::connectionCount</targetSymbol>
    </ADDITIONALINFO>
    <PATH></PATH>
  </DEFECT>
  <DEFECT>
    <SFA>
      <FILEPATH>E:\XBLAH\content\Mapbase\klepto\src\public\</FILEPATH>
      <FILENAME>saverestoretypes.h</FILENAME>
      <LINE>176</LINE>
      <COLUMN>0</COLUMN>
    </SFA>
    <DEFECTCODE>26495</DEFECTCODE>
    <DESCRIPTION>Variable 'saverestorelevelinfo_t::time__USE_VCR_MODE' is uninitialized. Always initialize a member variable (type.6).</DESCRIPTION>
    <FUNCTION>saverestorelevelinfo_t::{ctor}</FUNCTION>
    <DECORATED>??0saverestorelevelinfo_t@@QAE@XZ</DECORATED>
    <FUNCLINE>176</FUNCLINE>
    <ADDITIONALINFO>
      <targetSymbol>saverestorelevelinfo_t::time__USE_VCR_MODE</targetSymbol>
    </ADDITIONALINFO>
    <PATH></PATH>
  </DEFECT>
  <DEFECT>
    <SFA>
      <FILEPATH>E:\XBLAH\content\Mapbase\klepto\src\public\</FILEPATH>
      <FILENAME>saverestoretypes.h</FILENAME>
      <LINE>176</LINE>
      <COLUMN>0</COLUMN>
    </SFA>
    <DEFECTCODE>26495</DEFECTCODE>
    <DESCRIPTION>Variable 'saverestorelevelinfo_t::szLandmarkName' is uninitialized. Always initialize a member variable (type.6).</DESCRIPTION>
    <FUNCTION>saverestorelevelinfo_t::{ctor}</FUNCTION>
    <DECORATED>??0saverestorelevelinfo_t@@QAE@XZ</DECORATED>
    <FUNCLINE>176</FUNCLINE>
    <ADDITIONALINFO>
      <targetSymbol>saverestorelevelinfo_t::szLandmarkName</targetSymbol>
    </ADDITIONALINFO>
    <PATH></PATH>
  </DEFECT>
  <DEFECT>
    <SFA>
      <FILEPATH>E:\XBLAH\content\Mapbase\klepto\src\public\</FILEPATH>
      <FILENAME>saverestoretypes.h</FILENAME>
      <LINE>176</LINE>
      <COLUMN>0</COLUMN>
    </SFA>
    <DEFECTCODE>26495</DEFECTCODE>
    <DESCRIPTION>Variable 'saverestorelevelinfo_t::fUseLandmark' is uninitialized. Always initialize a member variable (type.6).</DESCRIPTION>
    <FUNCTION>saverestorelevelinfo_t::{ctor}</FUNCTION>
    <DECORATED>??0saverestorelevelinfo_t@@QAE@XZ</DECORATED>
    <FUNCLINE>176</FUNCLINE>
    <ADDITIONALINFO>
      <targetSymbol>saverestorelevelinfo_t::fUseLandmark</targetSymbol>
    </ADDITIONALINFO>
    <PATH></PATH>
  </DEFECT>
  <DEFECT>
    <SFA>
      <FILEPATH>E:\XBLAH\content\Mapbase\klepto\src\public\</FILEPATH>
      <FILENAME>saverestoretypes.h</FILENAME>
      <LINE>176</LINE>
      <COLUMN>0</COLUMN>
    </SFA>
    <DEFECTCODE>26495</DEFECTCODE>
    <DESCRIPTION>Variable 'saverestorelevelinfo_t::szCurrentMapName' is uninitialized. Always initialize a member variable (type.6).</DESCRIPTION>
    <FUNCTION>saverestorelevelinfo_t::{ctor}</FUNCTION>
    <DECORATED>??0saverestorelevelinfo_t@@QAE@XZ</DECORATED>
    <FUNCLINE>176</FUNCLINE>
    <ADDITIONALINFO>
      <targetSymbol>saverestorelevelinfo_t::szCurrentMapName</targetSymbol>
    </ADDITIONALINFO>
    <PATH></PATH>
  </DEFECT>
  <DEFECT>
    <SFA>
      <FILEPATH>E:\XBLAH\content\Mapbase\klepto\src\public\</FILEPATH>
      <FILENAME>saverestoretypes.h</FILENAME>
      <LINE>100</LINE>
      <COLUMN>0</COLUMN>
    </SFA>
    <DEFECTCODE>26495</DEFECTCODE>
    <DESCRIPTION>Variable 'levellist_t::landmarkName' is uninitialized. Always initialize a member variable (type.6).</DESCRIPTION>
    <FUNCTION>levellist_t::{ctor}</FUNCTION>
    <DECORATED>??0levellist_t@@QAE@XZ</DECORATED>
    <FUNCLINE>100</FUNCLINE>
    <ADDITIONALINFO>
      <targetSymbol>levellist_t::landmarkName</targetSymbol>
    </ADDITIONALINFO>
    <PATH></PATH>
  </DEFECT>
  <DEFECT>
    <SFA>
      <FILEPATH>E:\XBLAH\content\Mapbase\klepto\src\public\</FILEPATH>
      <FILENAME>saverestoretypes.h</FILENAME>
      <LINE>100</LINE>
      <COLUMN>0</COLUMN>
    </SFA>
    <DEFECTCODE>26495</DEFECTCODE>
    <DESCRIPTION>Variable 'levellist_t::mapName' is uninitialized. Always initialize a member variable (type.6).</DESCRIPTION>
    <FUNCTION>levellist_t::{ctor}</FUNCTION>
    <DECORATED>??0levellist_t@@QAE@XZ</DECORATED>
    <FUNCLINE>100</FUNCLINE>
    <ADDITIONALINFO>
      <targetSymbol>levellist_t::mapName</targetSymbol>
    </ADDITIONALINFO>
    <PATH></PATH>
  </DEFECT>
  <DEFECT>
    <SFA>
      <FILEPATH>E:\XBLAH\content\Mapbase\klepto\src\public\</FILEPATH>
      <FILENAME>saverestoretypes.h</FILENAME>
      <LINE>100</LINE>
      <COLUMN>0</COLUMN>
    </SFA>
    <DEFECTCODE>26495</DEFECTCODE>
    <DESCRIPTION>Variable 'levellist_t::pentLandmark' is uninitialized. Always initialize a member variable (type.6).</DESCRIPTION>
    <FUNCTION>levellist_t::{ctor}</FUNCTION>
    <DECORATED>??0levellist_t@@QAE@XZ</DECORATED>
    <FUNCLINE>100</FUNCLINE>
    <ADDITIONALINFO>
      <targetSymbol>levellist_t::pentLandmark</targetSymbol>
    </ADDITIONALINFO>
    <PATH></PATH>
  </DEFECT>
  <DEFECT>
    <SFA>
      <FILEPATH>E:\XBLAH\content\Mapbase\klepto\src\game\server\</FILEPATH>
      <FILENAME>ai_namespaces.h</FILENAME>
      <LINE>141</LINE>
      <COLUMN>1</COLUMN>
    </SFA>
    <DEFECTCODE>26495</DEFECTCODE>
    <DESCRIPTION>Variable 'CAI_ClassScheduleIdSpace::m_pszClassName' is uninitialized. Always initialize a member variable (type.6).</DESCRIPTION>
    <FUNCTION>CAI_ClassScheduleIdSpace::{ctor}</FUNCTION>
    <DECORATED>??0CAI_ClassScheduleIdSpace@@QAE@_N@Z</DECORATED>
    <FUNCLINE>141</FUNCLINE>
    <ADDITIONALINFO>
      <targetSymbol>CAI_ClassScheduleIdSpace::m_pszClassName</targetSymbol>
    </ADDITIONALINFO>
    <PATH></PATH>
  </DEFECT>
  <DEFECT>
    <SFA>
      <FILEPATH>E:\XBLAH\content\Mapbase\klepto\src\game\shared\</FILEPATH>
      <FILENAME>activitylist.h</FILENAME>
      <LINE>22</LINE>
      <COLUMN>1</COLUMN>
    </SFA>
    <DEFECTCODE>26495</DEFECTCODE>
    <DESCRIPTION>Variable 'CActivityRemap::activity' is uninitialized. Always initialize a member variable (type.6).</DESCRIPTION>
    <FUNCTION>CActivityRemap::{ctor}</FUNCTION>
    <DECORATED>??0CActivityRemap@@QAE@XZ</DECORATED>
    <FUNCLINE>22</FUNCLINE>
    <ADDITIONALINFO>
      <targetSymbol>CActivityRemap::activity</targetSymbol>
    </ADDITIONALINFO>
    <PATH></PATH>
  </DEFECT>
  <DEFECT>
    <SFA>
      <FILEPATH>E:\XBLAH\content\Mapbase\klepto\src\game\shared\</FILEPATH>
      <FILENAME>activitylist.h</FILENAME>
      <LINE>22</LINE>
      <COLUMN>1</COLUMN>
    </SFA>
    <DEFECTCODE>26495</DEFECTCODE>
    <DESCRIPTION>Variable 'CActivityRemap::mappedActivity' is uninitialized. Always initialize a member variable (type.6).</DESCRIPTION>
    <FUNCTION>CActivityRemap::{ctor}</FUNCTION>
    <DECORATED>??0CActivityRemap@@QAE@XZ</DECORATED>
    <FUNCLINE>22</FUNCLINE>
    <ADDITIONALINFO>
      <targetSymbol>CActivityRemap::mappedActivity</targetSymbol>
    </ADDITIONALINFO>
    <PATH></PATH>
  </DEFECT>
  <DEFECT>
    <SFA>
      <FILEPATH>E:\XBLAH\content\Mapbase\klepto\src\game\server\</FILEPATH>
      <FILENAME>baseentity.h</FILENAME>
      <LINE>227</LINE>
      <COLUMN>0</COLUMN>
    </SFA>
    <DEFECTCODE>26495</DEFECTCODE>
    <DESCRIPTION>Variable 'inputdata_t::pActivator' is uninitialized. Always initialize a member variable (type.6).</DESCRIPTION>
    <FUNCTION>inputdata_t::{ctor}</FUNCTION>
    <DECORATED>??0inputdata_t@@QAE@XZ</DECORATED>
    <FUNCLINE>227</FUNCLINE>
    <ADDITIONALINFO>
      <targetSymbol>inputdata_t::pActivator</targetSymbol>
    </ADDITIONALINFO>
    <PATH></PATH>
  </DEFECT>
  <DEFECT>
    <SFA>
      <FILEPATH>E:\XBLAH\content\Mapbase\klepto\src\game\server\</FILEPATH>
      <FILENAME>baseentity.h</FILENAME>
      <LINE>227</LINE>
      <COLUMN>0</COLUMN>
    </SFA>
    <DEFECTCODE>26495</DEFECTCODE>
    <DESCRIPTION>Variable 'inputdata_t::pCaller' is uninitialized. Always initialize a member variable (type.6).</DESCRIPTION>
    <FUNCTION>inputdata_t::{ctor}</FUNCTION>
    <DECORATED>??0inputdata_t@@QAE@XZ</DECORATED>
    <FUNCLINE>227</FUNCLINE>
    <ADDITIONALINFO>
      <targetSymbol>inputdata_t::pCaller</targetSymbol>
    </ADDITIONALINFO>
    <PATH></PATH>
  </DEFECT>
  <DEFECT>
    <SFA>
      <FILEPATH>E:\XBLAH\content\Mapbase\klepto\src\game\server\</FILEPATH>
      <FILENAME>baseentity.h</FILENAME>
      <LINE>227</LINE>
      <COLUMN>0</COLUMN>
    </SFA>
    <DEFECTCODE>26495</DEFECTCODE>
    <DESCRIPTION>Variable 'inputdata_t::nOutputID' is uninitialized. Always initialize a member variable (type.6).</DESCRIPTION>
    <FUNCTION>inputdata_t::{ctor}</FUNCTION>
    <DECORATED>??0inputdata_t@@QAE@XZ</DECORATED>
    <FUNCLINE>227</FUNCLINE>
    <ADDITIONALINFO>
      <targetSymbol>inputdata_t::nOutputID</targetSymbol>
    </ADDITIONALINFO>
    <PATH></PATH>
  </DEFECT>
  <DEFECT>
    <SFA>
      <FILEPATH>E:\XBLAH\content\Mapbase\klepto\src\game\server\</FILEPATH>
      <FILENAME>baseentity.cpp</FILENAME>
      <LINE>5308</LINE>
      <COLUMN>0</COLUMN>
    </SFA>
    <DEFECTCODE>26495</DEFECTCODE>
    <DESCRIPTION>Variable 'TeleportListEntry_t::pEntity' is uninitialized. Always initialize a member variable (type.6).</DESCRIPTION>
    <FUNCTION>TeleportListEntry_t::{ctor}</FUNCTION>
    <DECORATED>??0TeleportListEntry_t@@QAE@XZ</DECORATED>
    <FUNCLINE>5308</FUNCLINE>
    <ADDITIONALINFO>
      <targetSymbol>TeleportListEntry_t::pEntity</targetSymbol>
    </ADDITIONALINFO>
    <PATH></PATH>
  </DEFECT>
  <DEFECT>
    <SFA>
      <FILEPATH>E:\XBLAH\content\Mapbase\klepto\src\game\server\</FILEPATH>
      <FILENAME>baseentity.cpp</FILENAME>
      <LINE>8112</LINE>
      <COLUMN>24</COLUMN>
    </SFA>
    <DEFECTCODE>6001</DEFECTCODE>
    <DESCRIPTION>Using uninitialized memory 'data'.</DESCRIPTION>
    <FUNCTION>CBaseEntity::InputReplaceOutput</FUNCTION>
    <DECORATED>?InputReplaceOutput@CBaseEntity@@QAEXAAUinputdata_t@@@Z</DECORATED>
    <FUNCLINE>8095</FUNCLINE>
    <PROBABILITY>1</PROBABILITY>
    <RANK>3</RANK>
    <CATEGORY>
      <RULECATEGORY>mspft</RULECATEGORY>
    </CATEGORY>
    <PATH>
      <SFA>
        <FILEPATH>E:\XBLAH\content\Mapbase\klepto\src\game\server\</FILEPATH>
        <FILENAME>baseentity.cpp</FILENAME>
        <LINE>8097</LINE>
        <COLUMN>6</COLUMN>
      </SFA>
      <SFA>
        <FILEPATH>E:\XBLAH\content\Mapbase\klepto\src\game\server\</FILEPATH>
        <FILENAME>baseentity.cpp</FILENAME>
        <LINE>8098</LINE>
        <COLUMN>10</COLUMN>
      </SFA>
      <SFA>
        <FILEPATH>E:\XBLAH\content\Mapbase\klepto\src\game\server\</FILEPATH>
        <FILENAME>baseentity.cpp</FILENAME>
        <LINE>8099</LINE>
        <COLUMN>5</COLUMN>
      </SFA>
      <SFA>
        <FILEPATH>E:\XBLAH\content\Mapbase\klepto\src\game\server\</FILEPATH>
        <FILENAME>baseentity.cpp</FILENAME>
        <LINE>8102</LINE>
        <COLUMN>5</COLUMN>
      </SFA>
      <SFA>
        <FILEPATH>E:\XBLAH\content\Mapbase\klepto\src\game\server\</FILEPATH>
        <FILENAME>baseentity.cpp</FILENAME>
        <LINE>8103</LINE>
        <COLUMN>7</COLUMN>
        <KEYEVENT>
          <ID>1</ID>
          <KIND>declaration</KIND>
          <IMPORTANCE>Essential</IMPORTANCE>
          <MESSAGE>'data' is not initialized</MESSAGE>
        </KEYEVENT>
      </SFA>
      <SFA>
        <FILEPATH>E:\XBLAH\content\Mapbase\klepto\src\game\server\</FILEPATH>
        <FILENAME>baseentity.cpp</FILENAME>
        <LINE>8104</LINE>
        <COLUMN>7</COLUMN>
      </SFA>
      <SFA>
        <FILEPATH>E:\XBLAH\content\Mapbase\klepto\src\game\server\</FILEPATH>
        <FILENAME>baseentity.cpp</FILENAME>
        <LINE>8105</LINE>
        <COLUMN>16</COLUMN>
        <KEYEVENT>
          <ID>2</ID>
          <KIND>branch</KIND>
          <IMPORTANCE>Full</IMPORTANCE>
          <MESSAGE>Skip this loop, (assume 'sToken&amp;&amp;iter&lt;2' is false)</MESSAGE>
        </KEYEVENT>
      </SFA>
      <SFA>
        <FILEPATH>E:\XBLAH\content\Mapbase\klepto\src\game\server\</FILEPATH>
        <FILENAME>baseentity.cpp</FILENAME>
        <LINE>8112</LINE>
        <COLUMN>13</COLUMN>
      </SFA>
      <SFA>
        <FILEPATH>E:\XBLAH\content\Mapbase\klepto\src\game\server\</FILEPATH>
        <FILENAME>baseentity.cpp</FILENAME>
        <LINE>8113</LINE>
        <COLUMN>13</COLUMN>
      </SFA>
      <SFA>
        <FILEPATH>E:\XBLAH\content\Mapbase\klepto\src\game\server\</FILEPATH>
        <FILENAME>baseentity.cpp</FILENAME>
        <LINE>8112</LINE>
        <COLUMN>24</COLUMN>
        <KEYEVENT>
          <ID>3</ID>
          <KIND>usage</KIND>
          <IMPORTANCE>Essential</IMPORTANCE>
          <MESSAGE>'data' is used, but may not have been initialized</MESSAGE>
        </KEYEVENT>
      </SFA>
    </PATH>
  </DEFECT>
  <DEFECT>
    <SFA>
      <FILEPATH>E:\XBLAH\content\Mapbase\klepto\src\game\server\</FILEPATH>
      <FILENAME>baseentity.cpp</FILENAME>
      <LINE>9946</LINE>
      <COLUMN>25</COLUMN>
    </SFA>
    <DEFECTCODE>6255</DEFECTCODE>
    <DESCRIPTION>`_alloca` indicates failure by raising a stack overflow exception.  Consider using _malloca instead.</DESCRIPTION>
    <FUNCTION>CBaseEntity::GetScriptInstance</FUNCTION>
    <DECORATED>?GetScriptInstance@CBaseEntity@@QAEPAUHSCRIPT__@@XZ</DECORATED>
    <FUNCLINE>9940</FUNCLINE>
    <PATH></PATH>
  </DEFECT>
</DEFECTS>