<?xml version="1.0" encoding="UTF-8"?>
<DEFECTS>
  <DEFECT>
    <SFA>
      <FILEPATH>E:\XBLAH\content\Mapbase\klepto\src\game\server\</FILEPATH>
      <FILENAME>movie_display.cpp</FILENAME>
      <LINE>24</LINE>
      <COLUMN>1</COLUMN>
    </SFA>
    <DEFECTCODE>26495</DEFECTCODE>
    <DESCRIPTION>Variable 'CMovieDisplay::m_iScreenHeight' is uninitialized. Always initialize a member variable (type.6).</DESCRIPTION>
    <FUNCTION>CMovieDisplay::{ctor}</FUNCTION>
    <DECORATED>??0CMovieDisplay@@QAE@XZ</DECORATED>
    <FUNCLINE>24</FUNCLINE>
    <ADDITIONALINFO>
      <targetSymbol>CMovieDisplay::m_iScreenHeight</targetSymbol>
    </ADDITIONALINFO>
    <PATH></PATH>
  </DEFECT>
  <DEFECT>
    <SFA>
      <FILEPATH>E:\XBLAH\content\Mapbase\klepto\src\game\server\</FILEPATH>
      <FILENAME>movie_display.cpp</FILENAME>
      <LINE>24</LINE>
      <COLUMN>1</COLUMN>
    </SFA>
    <DEFECTCODE>26495</DEFECTCODE>
    <DESCRIPTION>Variable 'CMovieDisplay::m_strGroupName' is uninitialized. Always initialize a member variable (type.6).</DESCRIPTION>
    <FUNCTION>CMovieDisplay::{ctor}</FUNCTION>
    <DECORATED>??0CMovieDisplay@@QAE@XZ</DECORATED>
    <FUNCLINE>24</FUNCLINE>
    <ADDITIONALINFO>
      <targetSymbol>CMovieDisplay::m_strGroupName</targetSymbol>
    </ADDITIONALINFO>
    <PATH></PATH>
  </DEFECT>
  <DEFECT>
    <SFA>
      <FILEPATH>E:\XBLAH\content\Mapbase\klepto\src\game\server\</FILEPATH>
      <FILENAME>movie_display.cpp</FILENAME>
      <LINE>24</LINE>
      <COLUMN>1</COLUMN>
    </SFA>
    <DEFECTCODE>26495</DEFECTCODE>
    <DESCRIPTION>Variable 'CMovieDisplay::m_strMovieFilename' is uninitialized. Always initialize a member variable (type.6).</DESCRIPTION>
    <FUNCTION>CMovieDisplay::{ctor}</FUNCTION>
    <DECORATED>??0CMovieDisplay@@QAE@XZ</DECORATED>
    <FUNCLINE>24</FUNCLINE>
    <ADDITIONALINFO>
      <targetSymbol>CMovieDisplay::m_strMovieFilename</targetSymbol>
    </ADDITIONALINFO>
    <PATH></PATH>
  </DEFECT>
  <DEFECT>
    <SFA>
      <FILEPATH>E:\XBLAH\content\Mapbase\klepto\src\game\server\</FILEPATH>
      <FILENAME>movie_display.cpp</FILENAME>
      <LINE>24</LINE>
      <COLUMN>1</COLUMN>
    </SFA>
    <DEFECTCODE>26495</DEFECTCODE>
    <DESCRIPTION>Variable 'CMovieDisplay::m_iScreenWidth' is uninitialized. Always initialize a member variable (type.6).</DESCRIPTION>
    <FUNCTION>CMovieDisplay::{ctor}</FUNCTION>
    <DECORATED>??0CMovieDisplay@@QAE@XZ</DECORATED>
    <FUNCLINE>24</FUNCLINE>
    <ADDITIONALINFO>
      <targetSymbol>CMovieDisplay::m_iScreenWidth</targetSymbol>
    </ADDITIONALINFO>
    <PATH></PATH>
  </DEFECT>
  <DEFECT>
    <SFA>
      <FILEPATH>E:\XBLAH\content\Mapbase\klepto\src\game\server\</FILEPATH>
      <FILENAME>movie_display.cpp</FILENAME>
      <LINE>24</LINE>
      <COLUMN>1</COLUMN>
    </SFA>
    <DEFECTCODE>26495</DEFECTCODE>
    <DESCRIPTION>Variable 'CMovieDisplay::m_bDoFullTransmit' is uninitialized. Always initialize a member variable (type.6).</DESCRIPTION>
    <FUNCTION>CMovieDisplay::{ctor}</FUNCTION>
    <DECORATED>??0CMovieDisplay@@QAE@XZ</DECORATED>
    <FUNCLINE>24</FUNCLINE>
    <ADDITIONALINFO>
      <targetSymbol>CMovieDisplay::m_bDoFullTransmit</targetSymbol>
    </ADDITIONALINFO>
    <PATH></PATH>
  </DEFECT>
  <DEFECT>
    <SFA>
      <FILEPATH>E:\XBLAH\content\Mapbase\klepto\src\game\server\</FILEPATH>
      <FILENAME>movie_display.cpp</FILENAME>
      <LINE>365</LINE>
      <COLUMN>59</COLUMN>
    </SFA>
    <DEFECTCODE>6011</DEFECTCODE>
    <DESCRIPTION>Dereferencing NULL pointer 'pScreen'. </DESCRIPTION>
    <FUNCTION>CMovieDisplay::RestoreControlPanels</FUNCTION>
    <DECORATED>?RestoreControlPanels@CMovieDisplay@@AAEXXZ</DECORATED>
    <FUNCLINE>348</FUNCLINE>
    <PROBABILITY>1</PROBABILITY>
    <RANK>4</RANK>
    <CATEGORY>
      <RULECATEGORY>mspft</RULECATEGORY>
    </CATEGORY>
    <PATH>
      <SFA>
        <FILEPATH>E:\XBLAH\content\Mapbase\klepto\src\game\server\</FILEPATH>
        <FILENAME>movie_display.cpp</FILENAME>
        <LINE>350</LINE>
        <COLUMN>5</COLUMN>
      </SFA>
      <SFA>
        <FILEPATH>E:\XBLAH\content\Mapbase\klepto\src\game\server\</FILEPATH>
        <FILENAME>movie_display.cpp</FILENAME>
        <LINE>351</LINE>
        <COLUMN>14</COLUMN>
      </SFA>
      <SFA>
        <FILEPATH>E:\XBLAH\content\Mapbase\klepto\src\game\server\</FILEPATH>
        <FILENAME>movie_display.cpp</FILENAME>
        <LINE>351</LINE>
        <COLUMN>19</COLUMN>
      </SFA>
      <SFA>
        <FILEPATH>E:\XBLAH\content\Mapbase\klepto\src\game\server\</FILEPATH>
        <FILENAME>movie_display.cpp</FILENAME>
        <LINE>353</LINE>
        <COLUMN>14</COLUMN>
      </SFA>
      <SFA>
        <FILEPATH>E:\XBLAH\content\Mapbase\klepto\src\game\server\</FILEPATH>
        <FILENAME>movie_display.cpp</FILENAME>
        <LINE>354</LINE>
        <COLUMN>21</COLUMN>
      </SFA>
      <SFA>
        <FILEPATH>E:\XBLAH\content\Mapbase\klepto\src\game\server\</FILEPATH>
        <FILENAME>movie_display.cpp</FILENAME>
        <LINE>355</LINE>
        <COLUMN>6</COLUMN>
      </SFA>
      <SFA>
        <FILEPATH>E:\XBLAH\content\Mapbase\klepto\src\game\server\</FILEPATH>
        <FILENAME>movie_display.cpp</FILENAME>
        <LINE>358</LINE>
        <COLUMN>14</COLUMN>
      </SFA>
      <SFA>
        <FILEPATH>E:\XBLAH\content\Mapbase\klepto\src\game\server\</FILEPATH>
        <FILENAME>movie_display.cpp</FILENAME>
        <LINE>359</LINE>
        <COLUMN>26</COLUMN>
      </SFA>
      <SFA>
        <FILEPATH>E:\XBLAH\content\Mapbase\klepto\src\game\server\</FILEPATH>
        <FILENAME>movie_display.cpp</FILENAME>
        <LINE>360</LINE>
        <COLUMN>7</COLUMN>
      </SFA>
      <SFA>
        <FILEPATH>E:\XBLAH\content\Mapbase\klepto\src\game\server\</FILEPATH>
        <FILENAME>movie_display.cpp</FILENAME>
        <LINE>363</LINE>
        <COLUMN>15</COLUMN>
      </SFA>
      <SFA>
        <FILEPATH>E:\XBLAH\content\Mapbase\klepto\src\game\server\</FILEPATH>
        <FILENAME>movie_display.cpp</FILENAME>
        <LINE>365</LINE>
        <COLUMN>59</COLUMN>
        <KEYEVENT>
          <ID>1</ID>
          <KIND>declaration</KIND>
          <IMPORTANCE>Essential</IMPORTANCE>
          <MESSAGE>'pScreen' may be NULL</MESSAGE>
        </KEYEVENT>
      </SFA>
      <SFA>
        <FILEPATH>E:\XBLAH\content\Mapbase\klepto\src\game\server\</FILEPATH>
        <FILENAME>movie_display.cpp</FILENAME>
        <LINE>365</LINE>
        <COLUMN>59</COLUMN>
        <KEYEVENT>
          <ID>2</ID>
          <KIND>usage</KIND>
          <IMPORTANCE>Essential</IMPORTANCE>
          <MESSAGE>'pScreen' is dereferenced, but may still be NULL</MESSAGE>
        </KEYEVENT>
      </SFA>
    </PATH>
  </DEFECT>
</DEFECTS>