<?xml version="1.0" encoding="UTF-8"?>
<DEFECTS>
  <DEFECT>
    <SFA>
      <FILEPATH>E:\XBLAH\content\Mapbase\klepto\src\game\server\</FILEPATH>
      <FILENAME>ai_namespaces.h</FILENAME>
      <LINE>141</LINE>
      <COLUMN>1</COLUMN>
    </SFA>
    <DEFECTCODE>26495</DEFECTCODE>
    <DESCRIPTION>Variable 'CAI_ClassScheduleIdSpace::m_pszClassName' is uninitialized. Always initialize a member variable (type.6).</DESCRIPTION>
    <FUNCTION>CAI_ClassScheduleIdSpace::{ctor}</FUNCTION>
    <DECORATED>??0CAI_ClassScheduleIdSpace@@QAE@_N@Z</DECORATED>
    <FUNCLINE>141</FUNCLINE>
    <ADDITIONALINFO>
      <targetSymbol>CAI_ClassScheduleIdSpace::m_pszClassName</targetSymbol>
    </ADDITIONALINFO>
    <PATH></PATH>
  </DEFECT>
  <DEFECT>
    <SFA>
      <FILEPATH>E:\XBLAH\content\Mapbase\klepto\src\game\shared\</FILEPATH>
      <FILENAME>activitylist.h</FILENAME>
      <LINE>22</LINE>
      <COLUMN>1</COLUMN>
    </SFA>
    <DEFECTCODE>26495</DEFECTCODE>
    <DESCRIPTION>Variable 'CActivityRemap::mappedActivity' is uninitialized. Always initialize a member variable (type.6).</DESCRIPTION>
    <FUNCTION>CActivityRemap::{ctor}</FUNCTION>
    <DECORATED>??0CActivityRemap@@QAE@XZ</DECORATED>
    <FUNCLINE>22</FUNCLINE>
    <ADDITIONALINFO>
      <targetSymbol>CActivityRemap::mappedActivity</targetSymbol>
    </ADDITIONALINFO>
    <PATH></PATH>
  </DEFECT>
  <DEFECT>
    <SFA>
      <FILEPATH>E:\XBLAH\content\Mapbase\klepto\src\game\shared\</FILEPATH>
      <FILENAME>activitylist.h</FILENAME>
      <LINE>22</LINE>
      <COLUMN>1</COLUMN>
    </SFA>
    <DEFECTCODE>26495</DEFECTCODE>
    <DESCRIPTION>Variable 'CActivityRemap::activity' is uninitialized. Always initialize a member variable (type.6).</DESCRIPTION>
    <FUNCTION>CActivityRemap::{ctor}</FUNCTION>
    <DECORATED>??0CActivityRemap@@QAE@XZ</DECORATED>
    <FUNCLINE>22</FUNCLINE>
    <ADDITIONALINFO>
      <targetSymbol>CActivityRemap::activity</targetSymbol>
    </ADDITIONALINFO>
    <PATH></PATH>
  </DEFECT>
  <DEFECT>
    <SFA>
      <FILEPATH>E:\XBLAH\content\Mapbase\klepto\src\game\server\</FILEPATH>
      <FILENAME>ai_network.h</FILENAME>
      <LINE>55</LINE>
      <COLUMN>1</COLUMN>
    </SFA>
    <DEFECTCODE>26495</DEFECTCODE>
    <DESCRIPTION>Variable 'AI_NearNode_t::nodeIndex' is uninitialized. Always initialize a member variable (type.6).</DESCRIPTION>
    <FUNCTION>AI_NearNode_t::{ctor}</FUNCTION>
    <DECORATED>??0AI_NearNode_t@@QAE@XZ</DECORATED>
    <FUNCLINE>55</FUNCLINE>
    <ADDITIONALINFO>
      <targetSymbol>AI_NearNode_t::nodeIndex</targetSymbol>
    </ADDITIONALINFO>
    <PATH></PATH>
  </DEFECT>
  <DEFECT>
    <SFA>
      <FILEPATH>E:\XBLAH\content\Mapbase\klepto\src\game\server\</FILEPATH>
      <FILENAME>ai_network.h</FILENAME>
      <LINE>55</LINE>
      <COLUMN>1</COLUMN>
    </SFA>
    <DEFECTCODE>26495</DEFECTCODE>
    <DESCRIPTION>Variable 'AI_NearNode_t::dist' is uninitialized. Always initialize a member variable (type.6).</DESCRIPTION>
    <FUNCTION>AI_NearNode_t::{ctor}</FUNCTION>
    <DECORATED>??0AI_NearNode_t@@QAE@XZ</DECORATED>
    <FUNCLINE>55</FUNCLINE>
    <ADDITIONALINFO>
      <targetSymbol>AI_NearNode_t::dist</targetSymbol>
    </ADDITIONALINFO>
    <PATH></PATH>
  </DEFECT>
  <DEFECT>
    <SFA>
      <FILEPATH>E:\XBLAH\content\Mapbase\klepto\src\game\server\</FILEPATH>
      <FILENAME>ai_pathfinder.h</FILENAME>
      <LINE>51</LINE>
      <COLUMN>1</COLUMN>
    </SFA>
    <DEFECTCODE>26495</DEFECTCODE>
    <DESCRIPTION>Variable 'CAI_Pathfinder::m_bIgnoreStaleLinks' is uninitialized. Always initialize a member variable (type.6).</DESCRIPTION>
    <FUNCTION>CAI_Pathfinder::{ctor}</FUNCTION>
    <DECORATED>??0CAI_Pathfinder@@QAE@PAVCAI_BaseNPC@@@Z</DECORATED>
    <FUNCLINE>51</FUNCLINE>
    <ADDITIONALINFO>
      <targetSymbol>CAI_Pathfinder::m_bIgnoreStaleLinks</targetSymbol>
    </ADDITIONALINFO>
    <PATH></PATH>
  </DEFECT>
  <DEFECT>
    <SFA>
      <FILEPATH>E:\XBLAH\content\Mapbase\klepto\src\game\server\</FILEPATH>
      <FILENAME>ai_blended_movement.h</FILENAME>
      <LINE>28</LINE>
      <COLUMN>1</COLUMN>
    </SFA>
    <DEFECTCODE>26495</DEFECTCODE>
    <DESCRIPTION>Variable 'CAI_BlendedMotor::m_flNextTurnGesture' is uninitialized. Always initialize a member variable (type.6).</DESCRIPTION>
    <FUNCTION>CAI_BlendedMotor::{ctor}</FUNCTION>
    <DECORATED>??0CAI_BlendedMotor@@QAE@PAVCAI_BaseNPC@@@Z</DECORATED>
    <FUNCLINE>28</FUNCLINE>
    <ADDITIONALINFO>
      <targetSymbol>CAI_BlendedMotor::m_flNextTurnGesture</targetSymbol>
    </ADDITIONALINFO>
    <PATH></PATH>
  </DEFECT>
  <DEFECT>
    <SFA>
      <FILEPATH>E:\XBLAH\content\Mapbase\klepto\src\game\server\</FILEPATH>
      <FILENAME>ai_blended_movement.h</FILENAME>
      <LINE>28</LINE>
      <COLUMN>1</COLUMN>
    </SFA>
    <DEFECTCODE>26495</DEFECTCODE>
    <DESCRIPTION>Variable 'CAI_BlendedMotor::m_flCurrRate' is uninitialized. Always initialize a member variable (type.6).</DESCRIPTION>
    <FUNCTION>CAI_BlendedMotor::{ctor}</FUNCTION>
    <DECORATED>??0CAI_BlendedMotor@@QAE@PAVCAI_BaseNPC@@@Z</DECORATED>
    <FUNCLINE>28</FUNCLINE>
    <ADDITIONALINFO>
      <targetSymbol>CAI_BlendedMotor::m_flCurrRate</targetSymbol>
    </ADDITIONALINFO>
    <PATH></PATH>
  </DEFECT>
  <DEFECT>
    <SFA>
      <FILEPATH>E:\XBLAH\content\Mapbase\klepto\src\public\</FILEPATH>
      <FILENAME>bone_accessor.h</FILENAME>
      <LINE>68</LINE>
      <COLUMN>22</COLUMN>
    </SFA>
    <DEFECTCODE>26495</DEFECTCODE>
    <DESCRIPTION>Variable 'CBoneAccessor::m_ReadableBones' is uninitialized. Always initialize a member variable (type.6).</DESCRIPTION>
    <FUNCTION>CBoneAccessor::{ctor}</FUNCTION>
    <DECORATED>??0CBoneAccessor@@QAE@PAUmatrix3x4_t@@@Z</DECORATED>
    <FUNCLINE>68</FUNCLINE>
    <ADDITIONALINFO>
      <targetSymbol>CBoneAccessor::m_ReadableBones</targetSymbol>
    </ADDITIONALINFO>
    <PATH></PATH>
  </DEFECT>
  <DEFECT>
    <SFA>
      <FILEPATH>E:\XBLAH\content\Mapbase\klepto\src\public\</FILEPATH>
      <FILENAME>bone_accessor.h</FILENAME>
      <LINE>68</LINE>
      <COLUMN>22</COLUMN>
    </SFA>
    <DEFECTCODE>26495</DEFECTCODE>
    <DESCRIPTION>Variable 'CBoneAccessor::m_WritableBones' is uninitialized. Always initialize a member variable (type.6).</DESCRIPTION>
    <FUNCTION>CBoneAccessor::{ctor}</FUNCTION>
    <DECORATED>??0CBoneAccessor@@QAE@PAUmatrix3x4_t@@@Z</DECORATED>
    <FUNCLINE>68</FUNCLINE>
    <ADDITIONALINFO>
      <targetSymbol>CBoneAccessor::m_WritableBones</targetSymbol>
    </ADDITIONALINFO>
    <PATH></PATH>
  </DEFECT>
  <DEFECT>
    <SFA>
      <FILEPATH>E:\XBLAH\content\Mapbase\klepto\src\game\shared\</FILEPATH>
      <FILENAME>ragdoll_shared.h</FILENAME>
      <LINE>108</LINE>
      <COLUMN>1</COLUMN>
    </SFA>
    <DEFECTCODE>26495</DEFECTCODE>
    <DESCRIPTION>Variable 'CRagdollLRURetirement::m_iSimulatedRagdollCount' is uninitialized. Always initialize a member variable (type.6).</DESCRIPTION>
    <FUNCTION>CRagdollLRURetirement::{ctor}</FUNCTION>
    <DECORATED>??0CRagdollLRURetirement@@QAE@PBD@Z</DECORATED>
    <FUNCLINE>108</FUNCLINE>
    <ADDITIONALINFO>
      <targetSymbol>CRagdollLRURetirement::m_iSimulatedRagdollCount</targetSymbol>
    </ADDITIONALINFO>
    <PATH></PATH>
  </DEFECT>
  <DEFECT>
    <SFA>
      <FILEPATH>E:\XBLAH\content\Mapbase\klepto\src\game\shared\</FILEPATH>
      <FILENAME>ragdoll_shared.h</FILENAME>
      <LINE>108</LINE>
      <COLUMN>1</COLUMN>
    </SFA>
    <DEFECTCODE>26495</DEFECTCODE>
    <DESCRIPTION>Variable 'CRagdollLRURetirement::m_iRagdollCount' is uninitialized. Always initialize a member variable (type.6).</DESCRIPTION>
    <FUNCTION>CRagdollLRURetirement::{ctor}</FUNCTION>
    <DECORATED>??0CRagdollLRURetirement@@QAE@PBD@Z</DECORATED>
    <FUNCLINE>108</FUNCLINE>
    <ADDITIONALINFO>
      <targetSymbol>CRagdollLRURetirement::m_iRagdollCount</targetSymbol>
    </ADDITIONALINFO>
    <PATH></PATH>
  </DEFECT>
  <DEFECT>
    <SFA>
      <FILEPATH>E:\XBLAH\content\Mapbase\klepto\src\game\shared\</FILEPATH>
      <FILENAME>ragdoll_shared.h</FILENAME>
      <LINE>108</LINE>
      <COLUMN>1</COLUMN>
    </SFA>
    <DEFECTCODE>26495</DEFECTCODE>
    <DESCRIPTION>Variable 'CRagdollLRURetirement::m_iMaxRagdolls' is uninitialized. Always initialize a member variable (type.6).</DESCRIPTION>
    <FUNCTION>CRagdollLRURetirement::{ctor}</FUNCTION>
    <DECORATED>??0CRagdollLRURetirement@@QAE@PBD@Z</DECORATED>
    <FUNCLINE>108</FUNCLINE>
    <ADDITIONALINFO>
      <targetSymbol>CRagdollLRURetirement::m_iMaxRagdolls</targetSymbol>
    </ADDITIONALINFO>
    <PATH></PATH>
  </DEFECT>
  <DEFECT>
    <SFA>
      <FILEPATH>E:\XBLAH\content\Mapbase\klepto\src\game\server\</FILEPATH>
      <FILENAME>props.h</FILENAME>
      <LINE>387</LINE>
      <COLUMN>1</COLUMN>
    </SFA>
    <DEFECTCODE>26495</DEFECTCODE>
    <DESCRIPTION>Variable 'CPhysicsProp::m_bThrownByPlayer' is uninitialized. Always initialize a member variable (type.6).</DESCRIPTION>
    <FUNCTION>CPhysicsProp::{ctor}</FUNCTION>
    <DECORATED>??0CPhysicsProp@@QAE@XZ</DECORATED>
    <FUNCLINE>387</FUNCLINE>
    <ADDITIONALINFO>
      <targetSymbol>CPhysicsProp::m_bThrownByPlayer</targetSymbol>
    </ADDITIONALINFO>
    <PATH></PATH>
  </DEFECT>
  <DEFECT>
    <SFA>
      <FILEPATH>E:\XBLAH\content\Mapbase\klepto\src\game\server\</FILEPATH>
      <FILENAME>props.h</FILENAME>
      <LINE>387</LINE>
      <COLUMN>1</COLUMN>
    </SFA>
    <DEFECTCODE>26495</DEFECTCODE>
    <DESCRIPTION>Variable 'CPhysicsProp::m_damageType' is uninitialized. Always initialize a member variable (type.6).</DESCRIPTION>
    <FUNCTION>CPhysicsProp::{ctor}</FUNCTION>
    <DECORATED>??0CPhysicsProp@@QAE@XZ</DECORATED>
    <FUNCLINE>387</FUNCLINE>
    <ADDITIONALINFO>
      <targetSymbol>CPhysicsProp::m_damageType</targetSymbol>
    </ADDITIONALINFO>
    <PATH></PATH>
  </DEFECT>
  <DEFECT>
    <SFA>
      <FILEPATH>E:\XBLAH\content\Mapbase\klepto\src\game\server\</FILEPATH>
      <FILENAME>props.h</FILENAME>
      <LINE>387</LINE>
      <COLUMN>1</COLUMN>
    </SFA>
    <DEFECTCODE>26495</DEFECTCODE>
    <DESCRIPTION>Variable 'CPhysicsProp::m_bFirstCollisionAfterLaunch' is uninitialized. Always initialize a member variable (type.6).</DESCRIPTION>
    <FUNCTION>CPhysicsProp::{ctor}</FUNCTION>
    <DECORATED>??0CPhysicsProp@@QAE@XZ</DECORATED>
    <FUNCLINE>387</FUNCLINE>
    <ADDITIONALINFO>
      <targetSymbol>CPhysicsProp::m_bFirstCollisionAfterLaunch</targetSymbol>
    </ADDITIONALINFO>
    <PATH></PATH>
  </DEFECT>
  <DEFECT>
    <SFA>
      <FILEPATH>E:\XBLAH\content\Mapbase\klepto\src\game\server\</FILEPATH>
      <FILENAME>props.h</FILENAME>
      <LINE>387</LINE>
      <COLUMN>1</COLUMN>
    </SFA>
    <DEFECTCODE>26495</DEFECTCODE>
    <DESCRIPTION>Variable 'CPhysicsProp::m_damageToEnableMotion' is uninitialized. Always initialize a member variable (type.6).</DESCRIPTION>
    <FUNCTION>CPhysicsProp::{ctor}</FUNCTION>
    <DECORATED>??0CPhysicsProp@@QAE@XZ</DECORATED>
    <FUNCLINE>387</FUNCLINE>
    <ADDITIONALINFO>
      <targetSymbol>CPhysicsProp::m_damageToEnableMotion</targetSymbol>
    </ADDITIONALINFO>
    <PATH></PATH>
  </DEFECT>
  <DEFECT>
    <SFA>
      <FILEPATH>E:\XBLAH\content\Mapbase\klepto\src\game\server\</FILEPATH>
      <FILENAME>props.h</FILENAME>
      <LINE>387</LINE>
      <COLUMN>1</COLUMN>
    </SFA>
    <DEFECTCODE>26495</DEFECTCODE>
    <DESCRIPTION>Variable 'CPhysicsProp::m_iszOverrideScript' is uninitialized. Always initialize a member variable (type.6).</DESCRIPTION>
    <FUNCTION>CPhysicsProp::{ctor}</FUNCTION>
    <DECORATED>??0CPhysicsProp@@QAE@XZ</DECORATED>
    <FUNCLINE>387</FUNCLINE>
    <ADDITIONALINFO>
      <targetSymbol>CPhysicsProp::m_iszOverrideScript</targetSymbol>
    </ADDITIONALINFO>
    <PATH></PATH>
  </DEFECT>
  <DEFECT>
    <SFA>
      <FILEPATH>E:\XBLAH\content\Mapbase\klepto\src\game\server\</FILEPATH>
      <FILENAME>props.h</FILENAME>
      <LINE>387</LINE>
      <COLUMN>1</COLUMN>
    </SFA>
    <DEFECTCODE>26495</DEFECTCODE>
    <DESCRIPTION>Variable 'CPhysicsProp::m_massScale' is uninitialized. Always initialize a member variable (type.6).</DESCRIPTION>
    <FUNCTION>CPhysicsProp::{ctor}</FUNCTION>
    <DECORATED>??0CPhysicsProp@@QAE@XZ</DECORATED>
    <FUNCLINE>387</FUNCLINE>
    <ADDITIONALINFO>
      <targetSymbol>CPhysicsProp::m_massScale</targetSymbol>
    </ADDITIONALINFO>
    <PATH></PATH>
  </DEFECT>
  <DEFECT>
    <SFA>
      <FILEPATH>E:\XBLAH\content\Mapbase\klepto\src\game\server\</FILEPATH>
      <FILENAME>props.h</FILENAME>
      <LINE>387</LINE>
      <COLUMN>1</COLUMN>
    </SFA>
    <DEFECTCODE>26495</DEFECTCODE>
    <DESCRIPTION>Variable 'CPhysicsProp::m_inertiaScale' is uninitialized. Always initialize a member variable (type.6).</DESCRIPTION>
    <FUNCTION>CPhysicsProp::{ctor}</FUNCTION>
    <DECORATED>??0CPhysicsProp@@QAE@XZ</DECORATED>
    <FUNCLINE>387</FUNCLINE>
    <ADDITIONALINFO>
      <targetSymbol>CPhysicsProp::m_inertiaScale</targetSymbol>
    </ADDITIONALINFO>
    <PATH></PATH>
  </DEFECT>
  <DEFECT>
    <SFA>
      <FILEPATH>E:\XBLAH\content\Mapbase\klepto\src\game\server\</FILEPATH>
      <FILENAME>props.h</FILENAME>
      <LINE>387</LINE>
      <COLUMN>1</COLUMN>
    </SFA>
    <DEFECTCODE>26495</DEFECTCODE>
    <DESCRIPTION>Variable 'CPhysicsProp::m_flForceToEnableMotion' is uninitialized. Always initialize a member variable (type.6).</DESCRIPTION>
    <FUNCTION>CPhysicsProp::{ctor}</FUNCTION>
    <DECORATED>??0CPhysicsProp@@QAE@XZ</DECORATED>
    <FUNCLINE>387</FUNCLINE>
    <ADDITIONALINFO>
      <targetSymbol>CPhysicsProp::m_flForceToEnableMotion</targetSymbol>
    </ADDITIONALINFO>
    <PATH></PATH>
  </DEFECT>
  <DEFECT>
    <SFA>
      <FILEPATH>E:\XBLAH\content\Mapbase\klepto\src\game\server\</FILEPATH>
      <FILENAME>ai_behavior.h</FILENAME>
      <LINE>54</LINE>
      <COLUMN>1</COLUMN>
    </SFA>
    <DEFECTCODE>26495</DEFECTCODE>
    <DESCRIPTION>Variable 'CAI_BehaviorBase::m_fOverrode' is uninitialized. Always initialize a member variable (type.6).</DESCRIPTION>
    <FUNCTION>CAI_BehaviorBase::{ctor}</FUNCTION>
    <DECORATED>??0CAI_BehaviorBase@@QAE@PAVCAI_BaseNPC@@@Z</DECORATED>
    <FUNCLINE>54</FUNCLINE>
    <ADDITIONALINFO>
      <targetSymbol>CAI_BehaviorBase::m_fOverrode</targetSymbol>
    </ADDITIONALINFO>
    <PATH></PATH>
  </DEFECT>
  <DEFECT>
    <SFA>
      <FILEPATH>E:\XBLAH\content\Mapbase\klepto\src\game\server\</FILEPATH>
      <FILENAME>ai_behavior_assault.h</FILENAME>
      <LINE>60</LINE>
      <COLUMN>1</COLUMN>
    </SFA>
    <DEFECTCODE>26495</DEFECTCODE>
    <DESCRIPTION>Variable 'CRallyPoint::m_iPriority' is uninitialized. Always initialize a member variable (type.6).</DESCRIPTION>
    <FUNCTION>CRallyPoint::{ctor}</FUNCTION>
    <DECORATED>??0CRallyPoint@@QAE@XZ</DECORATED>
    <FUNCLINE>60</FUNCLINE>
    <ADDITIONALINFO>
      <targetSymbol>CRallyPoint::m_iPriority</targetSymbol>
    </ADDITIONALINFO>
    <PATH></PATH>
  </DEFECT>
  <DEFECT>
    <SFA>
      <FILEPATH>E:\XBLAH\content\Mapbase\klepto\src\game\server\</FILEPATH>
      <FILENAME>ai_behavior_assault.h</FILENAME>
      <LINE>60</LINE>
      <COLUMN>1</COLUMN>
    </SFA>
    <DEFECTCODE>26495</DEFECTCODE>
    <DESCRIPTION>Variable 'CRallyPoint::m_bIsUrgent' is uninitialized. Always initialize a member variable (type.6).</DESCRIPTION>
    <FUNCTION>CRallyPoint::{ctor}</FUNCTION>
    <DECORATED>??0CRallyPoint@@QAE@XZ</DECORATED>
    <FUNCLINE>60</FUNCLINE>
    <ADDITIONALINFO>
      <targetSymbol>CRallyPoint::m_bIsUrgent</targetSymbol>
    </ADDITIONALINFO>
    <PATH></PATH>
  </DEFECT>
  <DEFECT>
    <SFA>
      <FILEPATH>E:\XBLAH\content\Mapbase\klepto\src\game\server\</FILEPATH>
      <FILENAME>ai_behavior_assault.h</FILENAME>
      <LINE>60</LINE>
      <COLUMN>1</COLUMN>
    </SFA>
    <DEFECTCODE>26495</DEFECTCODE>
    <DESCRIPTION>Variable 'CRallyPoint::m_iStrictness' is uninitialized. Always initialize a member variable (type.6).</DESCRIPTION>
    <FUNCTION>CRallyPoint::{ctor}</FUNCTION>
    <DECORATED>??0CRallyPoint@@QAE@XZ</DECORATED>
    <FUNCLINE>60</FUNCLINE>
    <ADDITIONALINFO>
      <targetSymbol>CRallyPoint::m_iStrictness</targetSymbol>
    </ADDITIONALINFO>
    <PATH></PATH>
  </DEFECT>
  <DEFECT>
    <SFA>
      <FILEPATH>E:\XBLAH\content\Mapbase\klepto\src\game\server\</FILEPATH>
      <FILENAME>ai_behavior_assault.h</FILENAME>
      <LINE>60</LINE>
      <COLUMN>1</COLUMN>
    </SFA>
    <DEFECTCODE>26495</DEFECTCODE>
    <DESCRIPTION>Variable 'CRallyPoint::m_bForceCrouch' is uninitialized. Always initialize a member variable (type.6).</DESCRIPTION>
    <FUNCTION>CRallyPoint::{ctor}</FUNCTION>
    <DECORATED>??0CRallyPoint@@QAE@XZ</DECORATED>
    <FUNCLINE>60</FUNCLINE>
    <ADDITIONALINFO>
      <targetSymbol>CRallyPoint::m_bForceCrouch</targetSymbol>
    </ADDITIONALINFO>
    <PATH></PATH>
  </DEFECT>
  <DEFECT>
    <SFA>
      <FILEPATH>E:\XBLAH\content\Mapbase\klepto\src\game\server\</FILEPATH>
      <FILENAME>ai_behavior_assault.h</FILENAME>
      <LINE>60</LINE>
      <COLUMN>1</COLUMN>
    </SFA>
    <DEFECTCODE>26495</DEFECTCODE>
    <DESCRIPTION>Variable 'CRallyPoint::m_AssaultPointName' is uninitialized. Always initialize a member variable (type.6).</DESCRIPTION>
    <FUNCTION>CRallyPoint::{ctor}</FUNCTION>
    <DECORATED>??0CRallyPoint@@QAE@XZ</DECORATED>
    <FUNCLINE>60</FUNCLINE>
    <ADDITIONALINFO>
      <targetSymbol>CRallyPoint::m_AssaultPointName</targetSymbol>
    </ADDITIONALINFO>
    <PATH></PATH>
  </DEFECT>
  <DEFECT>
    <SFA>
      <FILEPATH>E:\XBLAH\content\Mapbase\klepto\src\game\server\</FILEPATH>
      <FILENAME>ai_behavior_assault.h</FILENAME>
      <LINE>60</LINE>
      <COLUMN>1</COLUMN>
    </SFA>
    <DEFECTCODE>26495</DEFECTCODE>
    <DESCRIPTION>Variable 'CRallyPoint::m_RallySequenceName' is uninitialized. Always initialize a member variable (type.6).</DESCRIPTION>
    <FUNCTION>CRallyPoint::{ctor}</FUNCTION>
    <DECORATED>??0CRallyPoint@@QAE@XZ</DECORATED>
    <FUNCLINE>60</FUNCLINE>
    <ADDITIONALINFO>
      <targetSymbol>CRallyPoint::m_RallySequenceName</targetSymbol>
    </ADDITIONALINFO>
    <PATH></PATH>
  </DEFECT>
  <DEFECT>
    <SFA>
      <FILEPATH>E:\XBLAH\content\Mapbase\klepto\src\game\server\</FILEPATH>
      <FILENAME>ai_behavior_assault.h</FILENAME>
      <LINE>60</LINE>
      <COLUMN>1</COLUMN>
    </SFA>
    <DEFECTCODE>26495</DEFECTCODE>
    <DESCRIPTION>Variable 'CRallyPoint::m_flAssaultDelay' is uninitialized. Always initialize a member variable (type.6).</DESCRIPTION>
    <FUNCTION>CRallyPoint::{ctor}</FUNCTION>
    <DECORATED>??0CRallyPoint@@QAE@XZ</DECORATED>
    <FUNCLINE>60</FUNCLINE>
    <ADDITIONALINFO>
      <targetSymbol>CRallyPoint::m_flAssaultDelay</targetSymbol>
    </ADDITIONALINFO>
    <PATH></PATH>
  </DEFECT>
  <DEFECT>
    <SFA>
      <FILEPATH>E:\XBLAH\content\Mapbase\klepto\src\game\server\</FILEPATH>
      <FILENAME>ai_behavior_assault.h</FILENAME>
      <LINE>129</LINE>
      <COLUMN>1</COLUMN>
    </SFA>
    <DEFECTCODE>26495</DEFECTCODE>
    <DESCRIPTION>Variable 'CAssaultPoint::m_NextAssaultPointName' is uninitialized. Always initialize a member variable (type.6).</DESCRIPTION>
    <FUNCTION>CAssaultPoint::{ctor}</FUNCTION>
    <DECORATED>??0CAssaultPoint@@QAE@XZ</DECORATED>
    <FUNCLINE>129</FUNCLINE>
    <ADDITIONALINFO>
      <targetSymbol>CAssaultPoint::m_NextAssaultPointName</targetSymbol>
    </ADDITIONALINFO>
    <PATH></PATH>
  </DEFECT>
  <DEFECT>
    <SFA>
      <FILEPATH>E:\XBLAH\content\Mapbase\klepto\src\game\server\</FILEPATH>
      <FILENAME>ai_behavior_assault.h</FILENAME>
      <LINE>129</LINE>
      <COLUMN>1</COLUMN>
    </SFA>
    <DEFECTCODE>26495</DEFECTCODE>
    <DESCRIPTION>Variable 'CAssaultPoint::m_bAllowDiversion' is uninitialized. Always initialize a member variable (type.6).</DESCRIPTION>
    <FUNCTION>CAssaultPoint::{ctor}</FUNCTION>
    <DECORATED>??0CAssaultPoint@@QAE@XZ</DECORATED>
    <FUNCLINE>129</FUNCLINE>
    <ADDITIONALINFO>
      <targetSymbol>CAssaultPoint::m_bAllowDiversion</targetSymbol>
    </ADDITIONALINFO>
    <PATH></PATH>
  </DEFECT>
  <DEFECT>
    <SFA>
      <FILEPATH>E:\XBLAH\content\Mapbase\klepto\src\game\server\</FILEPATH>
      <FILENAME>ai_behavior_assault.h</FILENAME>
      <LINE>129</LINE>
      <COLUMN>1</COLUMN>
    </SFA>
    <DEFECTCODE>26495</DEFECTCODE>
    <DESCRIPTION>Variable 'CAssaultPoint::m_bNeverTimeout' is uninitialized. Always initialize a member variable (type.6).</DESCRIPTION>
    <FUNCTION>CAssaultPoint::{ctor}</FUNCTION>
    <DECORATED>??0CAssaultPoint@@QAE@XZ</DECORATED>
    <FUNCLINE>129</FUNCLINE>
    <ADDITIONALINFO>
      <targetSymbol>CAssaultPoint::m_bNeverTimeout</targetSymbol>
    </ADDITIONALINFO>
    <PATH></PATH>
  </DEFECT>
  <DEFECT>
    <SFA>
      <FILEPATH>E:\XBLAH\content\Mapbase\klepto\src\game\server\</FILEPATH>
      <FILENAME>ai_behavior_assault.h</FILENAME>
      <LINE>129</LINE>
      <COLUMN>1</COLUMN>
    </SFA>
    <DEFECTCODE>26495</DEFECTCODE>
    <DESCRIPTION>Variable 'CAssaultPoint::m_flAllowDiversionRadius' is uninitialized. Always initialize a member variable (type.6).</DESCRIPTION>
    <FUNCTION>CAssaultPoint::{ctor}</FUNCTION>
    <DECORATED>??0CAssaultPoint@@QAE@XZ</DECORATED>
    <FUNCLINE>129</FUNCLINE>
    <ADDITIONALINFO>
      <targetSymbol>CAssaultPoint::m_flAllowDiversionRadius</targetSymbol>
    </ADDITIONALINFO>
    <PATH></PATH>
  </DEFECT>
  <DEFECT>
    <SFA>
      <FILEPATH>E:\XBLAH\content\Mapbase\klepto\src\game\server\</FILEPATH>
      <FILENAME>ai_behavior_assault.h</FILENAME>
      <LINE>129</LINE>
      <COLUMN>1</COLUMN>
    </SFA>
    <DEFECTCODE>26495</DEFECTCODE>
    <DESCRIPTION>Variable 'CAssaultPoint::m_bInputForcedClear' is uninitialized. Always initialize a member variable (type.6).</DESCRIPTION>
    <FUNCTION>CAssaultPoint::{ctor}</FUNCTION>
    <DECORATED>??0CAssaultPoint@@QAE@XZ</DECORATED>
    <FUNCLINE>129</FUNCLINE>
    <ADDITIONALINFO>
      <targetSymbol>CAssaultPoint::m_bInputForcedClear</targetSymbol>
    </ADDITIONALINFO>
    <PATH></PATH>
  </DEFECT>
  <DEFECT>
    <SFA>
      <FILEPATH>E:\XBLAH\content\Mapbase\klepto\src\game\server\</FILEPATH>
      <FILENAME>ai_behavior_assault.h</FILENAME>
      <LINE>129</LINE>
      <COLUMN>1</COLUMN>
    </SFA>
    <DEFECTCODE>26495</DEFECTCODE>
    <DESCRIPTION>Variable 'CAssaultPoint::m_bIsUrgent' is uninitialized. Always initialize a member variable (type.6).</DESCRIPTION>
    <FUNCTION>CAssaultPoint::{ctor}</FUNCTION>
    <DECORATED>??0CAssaultPoint@@QAE@XZ</DECORATED>
    <FUNCLINE>129</FUNCLINE>
    <ADDITIONALINFO>
      <targetSymbol>CAssaultPoint::m_bIsUrgent</targetSymbol>
    </ADDITIONALINFO>
    <PATH></PATH>
  </DEFECT>
  <DEFECT>
    <SFA>
      <FILEPATH>E:\XBLAH\content\Mapbase\klepto\src\game\server\</FILEPATH>
      <FILENAME>ai_behavior_assault.h</FILENAME>
      <LINE>129</LINE>
      <COLUMN>1</COLUMN>
    </SFA>
    <DEFECTCODE>26495</DEFECTCODE>
    <DESCRIPTION>Variable 'CAssaultPoint::m_flAssaultTimeout' is uninitialized. Always initialize a member variable (type.6).</DESCRIPTION>
    <FUNCTION>CAssaultPoint::{ctor}</FUNCTION>
    <DECORATED>??0CAssaultPoint@@QAE@XZ</DECORATED>
    <FUNCLINE>129</FUNCLINE>
    <ADDITIONALINFO>
      <targetSymbol>CAssaultPoint::m_flAssaultTimeout</targetSymbol>
    </ADDITIONALINFO>
    <PATH></PATH>
  </DEFECT>
  <DEFECT>
    <SFA>
      <FILEPATH>E:\XBLAH\content\Mapbase\klepto\src\game\server\</FILEPATH>
      <FILENAME>ai_behavior_assault.h</FILENAME>
      <LINE>129</LINE>
      <COLUMN>1</COLUMN>
    </SFA>
    <DEFECTCODE>26495</DEFECTCODE>
    <DESCRIPTION>Variable 'CAssaultPoint::m_bClearOnContact' is uninitialized. Always initialize a member variable (type.6).</DESCRIPTION>
    <FUNCTION>CAssaultPoint::{ctor}</FUNCTION>
    <DECORATED>??0CAssaultPoint@@QAE@XZ</DECORATED>
    <FUNCLINE>129</FUNCLINE>
    <ADDITIONALINFO>
      <targetSymbol>CAssaultPoint::m_bClearOnContact</targetSymbol>
    </ADDITIONALINFO>
    <PATH></PATH>
  </DEFECT>
  <DEFECT>
    <SFA>
      <FILEPATH>E:\XBLAH\content\Mapbase\klepto\src\game\server\</FILEPATH>
      <FILENAME>ai_behavior_assault.h</FILENAME>
      <LINE>129</LINE>
      <COLUMN>1</COLUMN>
    </SFA>
    <DEFECTCODE>26495</DEFECTCODE>
    <DESCRIPTION>Variable 'CAssaultPoint::m_AssaultHintGroup' is uninitialized. Always initialize a member variable (type.6).</DESCRIPTION>
    <FUNCTION>CAssaultPoint::{ctor}</FUNCTION>
    <DECORATED>??0CAssaultPoint@@QAE@XZ</DECORATED>
    <FUNCLINE>129</FUNCLINE>
    <ADDITIONALINFO>
      <targetSymbol>CAssaultPoint::m_AssaultHintGroup</targetSymbol>
    </ADDITIONALINFO>
    <PATH></PATH>
  </DEFECT>
  <DEFECT>
    <SFA>
      <FILEPATH>E:\XBLAH\content\Mapbase\klepto\src\game\server\</FILEPATH>
      <FILENAME>ai_behavior_assault.h</FILENAME>
      <LINE>129</LINE>
      <COLUMN>1</COLUMN>
    </SFA>
    <DEFECTCODE>26495</DEFECTCODE>
    <DESCRIPTION>Variable 'CAssaultPoint::m_flTimeLastUsed' is uninitialized. Always initialize a member variable (type.6).</DESCRIPTION>
    <FUNCTION>CAssaultPoint::{ctor}</FUNCTION>
    <DECORATED>??0CAssaultPoint@@QAE@XZ</DECORATED>
    <FUNCLINE>129</FUNCLINE>
    <ADDITIONALINFO>
      <targetSymbol>CAssaultPoint::m_flTimeLastUsed</targetSymbol>
    </ADDITIONALINFO>
    <PATH></PATH>
  </DEFECT>
  <DEFECT>
    <SFA>
      <FILEPATH>E:\XBLAH\content\Mapbase\klepto\src\game\server\</FILEPATH>
      <FILENAME>ai_behavior_assault.h</FILENAME>
      <LINE>129</LINE>
      <COLUMN>1</COLUMN>
    </SFA>
    <DEFECTCODE>26495</DEFECTCODE>
    <DESCRIPTION>Variable 'CAssaultPoint::m_iStrictness' is uninitialized. Always initialize a member variable (type.6).</DESCRIPTION>
    <FUNCTION>CAssaultPoint::{ctor}</FUNCTION>
    <DECORATED>??0CAssaultPoint@@QAE@XZ</DECORATED>
    <FUNCLINE>129</FUNCLINE>
    <ADDITIONALINFO>
      <targetSymbol>CAssaultPoint::m_iStrictness</targetSymbol>
    </ADDITIONALINFO>
    <PATH></PATH>
  </DEFECT>
  <DEFECT>
    <SFA>
      <FILEPATH>E:\XBLAH\content\Mapbase\klepto\src\game\server\</FILEPATH>
      <FILENAME>ai_behavior_assault.h</FILENAME>
      <LINE>129</LINE>
      <COLUMN>1</COLUMN>
    </SFA>
    <DEFECTCODE>26495</DEFECTCODE>
    <DESCRIPTION>Variable 'CAssaultPoint::m_bForceCrouch' is uninitialized. Always initialize a member variable (type.6).</DESCRIPTION>
    <FUNCTION>CAssaultPoint::{ctor}</FUNCTION>
    <DECORATED>??0CAssaultPoint@@QAE@XZ</DECORATED>
    <FUNCLINE>129</FUNCLINE>
    <ADDITIONALINFO>
      <targetSymbol>CAssaultPoint::m_bForceCrouch</targetSymbol>
    </ADDITIONALINFO>
    <PATH></PATH>
  </DEFECT>
  <DEFECT>
    <SFA>
      <FILEPATH>E:\XBLAH\content\Mapbase\klepto\src\game\shared\</FILEPATH>
      <FILENAME>effect_dispatch_data.h</FILENAME>
      <LINE>76</LINE>
      <COLUMN>1</COLUMN>
    </SFA>
    <DEFECTCODE>26495</DEFECTCODE>
    <DESCRIPTION>Variable 'CEffectData::m_iEffectName' is uninitialized. Always initialize a member variable (type.6).</DESCRIPTION>
    <FUNCTION>CEffectData::{ctor}</FUNCTION>
    <DECORATED>??0CEffectData@@QAE@XZ</DECORATED>
    <FUNCLINE>76</FUNCLINE>
    <ADDITIONALINFO>
      <targetSymbol>CEffectData::m_iEffectName</targetSymbol>
    </ADDITIONALINFO>
    <PATH></PATH>
  </DEFECT>
  <DEFECT>
    <SFA>
      <FILEPATH>E:\XBLAH\content\Mapbase\klepto\src\game\shared\</FILEPATH>
      <FILENAME>particle_parse.h</FILENAME>
      <LINE>50</LINE>
      <COLUMN>0</COLUMN>
    </SFA>
    <DEFECTCODE>26495</DEFECTCODE>
    <DESCRIPTION>Variable 'te_tf_particle_effects_control_point_t::m_eParticleAttachment' is uninitialized. Always initialize a member variable (type.6).</DESCRIPTION>
    <FUNCTION>te_tf_particle_effects_control_point_t::{ctor}</FUNCTION>
    <DECORATED>??0te_tf_particle_effects_control_point_t@@QAE@XZ</DECORATED>
    <FUNCLINE>50</FUNCLINE>
    <ADDITIONALINFO>
      <targetSymbol>te_tf_particle_effects_control_point_t::m_eParticleAttachment</targetSymbol>
    </ADDITIONALINFO>
    <PATH></PATH>
  </DEFECT>
  <DEFECT>
    <SFA>
      <FILEPATH>E:\XBLAH\content\Mapbase\klepto\src\game\server\hl2\</FILEPATH>
      <FILENAME>npc_antlionguard.cpp</FILENAME>
      <LINE>645</LINE>
      <COLUMN>19</COLUMN>
    </SFA>
    <DEFECTCODE>26495</DEFECTCODE>
    <DESCRIPTION>Variable 'CNPC_AntlionGuard::m_hCaveGlow' is uninitialized. Always initialize a member variable (type.6).</DESCRIPTION>
    <FUNCTION>CNPC_AntlionGuard::{ctor}</FUNCTION>
    <DECORATED>??0CNPC_AntlionGuard@@QAE@XZ</DECORATED>
    <FUNCLINE>645</FUNCLINE>
    <ADDITIONALINFO>
      <targetSymbol>CNPC_AntlionGuard::m_hCaveGlow</targetSymbol>
    </ADDITIONALINFO>
    <PATH></PATH>
  </DEFECT>
  <DEFECT>
    <SFA>
      <FILEPATH>E:\XBLAH\content\Mapbase\klepto\src\game\server\hl2\</FILEPATH>
      <FILENAME>npc_antlionguard.cpp</FILENAME>
      <LINE>645</LINE>
      <COLUMN>19</COLUMN>
    </SFA>
    <DEFECTCODE>26495</DEFECTCODE>
    <DESCRIPTION>Variable 'CNPC_AntlionGuard::m_strShoveTargets' is uninitialized. Always initialize a member variable (type.6).</DESCRIPTION>
    <FUNCTION>CNPC_AntlionGuard::{ctor}</FUNCTION>
    <DECORATED>??0CNPC_AntlionGuard@@QAE@XZ</DECORATED>
    <FUNCLINE>645</FUNCLINE>
    <ADDITIONALINFO>
      <targetSymbol>CNPC_AntlionGuard::m_strShoveTargets</targetSymbol>
    </ADDITIONALINFO>
    <PATH></PATH>
  </DEFECT>
  <DEFECT>
    <SFA>
      <FILEPATH>E:\XBLAH\content\Mapbase\klepto\src\game\server\hl2\</FILEPATH>
      <FILENAME>npc_antlionguard.cpp</FILENAME>
      <LINE>645</LINE>
      <COLUMN>19</COLUMN>
    </SFA>
    <DEFECTCODE>26495</DEFECTCODE>
    <DESCRIPTION>Variable 'CNPC_AntlionGuard::m_flNextHeavyFlinchTime' is uninitialized. Always initialize a member variable (type.6).</DESCRIPTION>
    <FUNCTION>CNPC_AntlionGuard::{ctor}</FUNCTION>
    <DECORATED>??0CNPC_AntlionGuard@@QAE@XZ</DECORATED>
    <FUNCLINE>645</FUNCLINE>
    <ADDITIONALINFO>
      <targetSymbol>CNPC_AntlionGuard::m_flNextHeavyFlinchTime</targetSymbol>
    </ADDITIONALINFO>
    <PATH></PATH>
  </DEFECT>
  <DEFECT>
    <SFA>
      <FILEPATH>E:\XBLAH\content\Mapbase\klepto\src\game\server\hl2\</FILEPATH>
      <FILENAME>npc_antlionguard.cpp</FILENAME>
      <LINE>645</LINE>
      <COLUMN>19</COLUMN>
    </SFA>
    <DEFECTCODE>26495</DEFECTCODE>
    <DESCRIPTION>Variable 'CNPC_AntlionGuard::m_pBreathSound' is uninitialized. Always initialize a member variable (type.6).</DESCRIPTION>
    <FUNCTION>CNPC_AntlionGuard::{ctor}</FUNCTION>
    <DECORATED>??0CNPC_AntlionGuard@@QAE@XZ</DECORATED>
    <FUNCLINE>645</FUNCLINE>
    <ADDITIONALINFO>
      <targetSymbol>CNPC_AntlionGuard::m_pBreathSound</targetSymbol>
    </ADDITIONALINFO>
    <PATH></PATH>
  </DEFECT>
  <DEFECT>
    <SFA>
      <FILEPATH>E:\XBLAH\content\Mapbase\klepto\src\game\server\hl2\</FILEPATH>
      <FILENAME>npc_antlionguard.cpp</FILENAME>
      <LINE>645</LINE>
      <COLUMN>19</COLUMN>
    </SFA>
    <DEFECTCODE>26495</DEFECTCODE>
    <DESCRIPTION>Variable 'CNPC_AntlionGuard::m_bIsBurrowed' is uninitialized. Always initialize a member variable (type.6).</DESCRIPTION>
    <FUNCTION>CNPC_AntlionGuard::{ctor}</FUNCTION>
    <DECORATED>??0CNPC_AntlionGuard@@QAE@XZ</DECORATED>
    <FUNCLINE>645</FUNCLINE>
    <ADDITIONALINFO>
      <targetSymbol>CNPC_AntlionGuard::m_bIsBurrowed</targetSymbol>
    </ADDITIONALINFO>
    <PATH></PATH>
  </DEFECT>
  <DEFECT>
    <SFA>
      <FILEPATH>E:\XBLAH\content\Mapbase\klepto\src\game\server\hl2\</FILEPATH>
      <FILENAME>npc_antlionguard.cpp</FILENAME>
      <LINE>645</LINE>
      <COLUMN>19</COLUMN>
    </SFA>
    <DEFECTCODE>26495</DEFECTCODE>
    <DESCRIPTION>Variable 'CNPC_AntlionGuard::m_bDecidedNotToStop' is uninitialized. Always initialize a member variable (type.6).</DESCRIPTION>
    <FUNCTION>CNPC_AntlionGuard::{ctor}</FUNCTION>
    <DECORATED>??0CNPC_AntlionGuard@@QAE@XZ</DECORATED>
    <FUNCLINE>645</FUNCLINE>
    <ADDITIONALINFO>
      <targetSymbol>CNPC_AntlionGuard::m_bDecidedNotToStop</targetSymbol>
    </ADDITIONALINFO>
    <PATH></PATH>
  </DEFECT>
  <DEFECT>
    <SFA>
      <FILEPATH>E:\XBLAH\content\Mapbase\klepto\src\game\server\hl2\</FILEPATH>
      <FILENAME>npc_antlionguard.cpp</FILENAME>
      <LINE>645</LINE>
      <COLUMN>19</COLUMN>
    </SFA>
    <DEFECTCODE>26495</DEFECTCODE>
    <DESCRIPTION>Variable 'CNPC_AntlionGuard::m_nFlinchActivity' is uninitialized. Always initialize a member variable (type.6).</DESCRIPTION>
    <FUNCTION>CNPC_AntlionGuard::{ctor}</FUNCTION>
    <DECORATED>??0CNPC_AntlionGuard@@QAE@XZ</DECORATED>
    <FUNCLINE>645</FUNCLINE>
    <ADDITIONALINFO>
      <targetSymbol>CNPC_AntlionGuard::m_nFlinchActivity</targetSymbol>
    </ADDITIONALINFO>
    <PATH></PATH>
  </DEFECT>
  <DEFECT>
    <SFA>
      <FILEPATH>E:\XBLAH\content\Mapbase\klepto\src\game\server\hl2\</FILEPATH>
      <FILENAME>npc_antlionguard.cpp</FILENAME>
      <LINE>645</LINE>
      <COLUMN>19</COLUMN>
    </SFA>
    <DEFECTCODE>26495</DEFECTCODE>
    <DESCRIPTION>Variable 'CNPC_AntlionGuard::m_pGrowlLowSound' is uninitialized. Always initialize a member variable (type.6).</DESCRIPTION>
    <FUNCTION>CNPC_AntlionGuard::{ctor}</FUNCTION>
    <DECORATED>??0CNPC_AntlionGuard@@QAE@XZ</DECORATED>
    <FUNCLINE>645</FUNCLINE>
    <ADDITIONALINFO>
      <targetSymbol>CNPC_AntlionGuard::m_pGrowlLowSound</targetSymbol>
    </ADDITIONALINFO>
    <PATH></PATH>
  </DEFECT>
  <DEFECT>
    <SFA>
      <FILEPATH>E:\XBLAH\content\Mapbase\klepto\src\game\server\hl2\</FILEPATH>
      <FILENAME>npc_antlionguard.cpp</FILENAME>
      <LINE>645</LINE>
      <COLUMN>19</COLUMN>
    </SFA>
    <DEFECTCODE>26495</DEFECTCODE>
    <DESCRIPTION>Variable 'CNPC_AntlionGuard::m_pGrowlIdleSound' is uninitialized. Always initialize a member variable (type.6).</DESCRIPTION>
    <FUNCTION>CNPC_AntlionGuard::{ctor}</FUNCTION>
    <DECORATED>??0CNPC_AntlionGuard@@QAE@XZ</DECORATED>
    <FUNCLINE>645</FUNCLINE>
    <ADDITIONALINFO>
      <targetSymbol>CNPC_AntlionGuard::m_pGrowlIdleSound</targetSymbol>
    </ADDITIONALINFO>
    <PATH></PATH>
  </DEFECT>
  <DEFECT>
    <SFA>
      <FILEPATH>E:\XBLAH\content\Mapbase\klepto\src\game\server\hl2\</FILEPATH>
      <FILENAME>npc_antlionguard.cpp</FILENAME>
      <LINE>645</LINE>
      <COLUMN>19</COLUMN>
    </SFA>
    <DEFECTCODE>26495</DEFECTCODE>
    <DESCRIPTION>Variable 'CNPC_AntlionGuard::m_flBreathTime' is uninitialized. Always initialize a member variable (type.6).</DESCRIPTION>
    <FUNCTION>CNPC_AntlionGuard::{ctor}</FUNCTION>
    <DECORATED>??0CNPC_AntlionGuard@@QAE@XZ</DECORATED>
    <FUNCLINE>645</FUNCLINE>
    <ADDITIONALINFO>
      <targetSymbol>CNPC_AntlionGuard::m_flBreathTime</targetSymbol>
    </ADDITIONALINFO>
    <PATH></PATH>
  </DEFECT>
  <DEFECT>
    <SFA>
      <FILEPATH>E:\XBLAH\content\Mapbase\klepto\src\game\server\hl2\</FILEPATH>
      <FILENAME>npc_antlionguard.cpp</FILENAME>
      <LINE>645</LINE>
      <COLUMN>19</COLUMN>
    </SFA>
    <DEFECTCODE>26495</DEFECTCODE>
    <DESCRIPTION>Variable 'CNPC_AntlionGuard::m_flPhysicsCheckTime' is uninitialized. Always initialize a member variable (type.6).</DESCRIPTION>
    <FUNCTION>CNPC_AntlionGuard::{ctor}</FUNCTION>
    <DECORATED>??0CNPC_AntlionGuard@@QAE@XZ</DECORATED>
    <FUNCLINE>645</FUNCLINE>
    <ADDITIONALINFO>
      <targetSymbol>CNPC_AntlionGuard::m_flPhysicsCheckTime</targetSymbol>
    </ADDITIONALINFO>
    <PATH></PATH>
  </DEFECT>
  <DEFECT>
    <SFA>
      <FILEPATH>E:\XBLAH\content\Mapbase\klepto\src\game\server\hl2\</FILEPATH>
      <FILENAME>npc_antlionguard.cpp</FILENAME>
      <LINE>645</LINE>
      <COLUMN>19</COLUMN>
    </SFA>
    <DEFECTCODE>26495</DEFECTCODE>
    <DESCRIPTION>Variable 'CNPC_AntlionGuard::m_flAngerNoiseTime' is uninitialized. Always initialize a member variable (type.6).</DESCRIPTION>
    <FUNCTION>CNPC_AntlionGuard::{ctor}</FUNCTION>
    <DECORATED>??0CNPC_AntlionGuard@@QAE@XZ</DECORATED>
    <FUNCLINE>645</FUNCLINE>
    <ADDITIONALINFO>
      <targetSymbol>CNPC_AntlionGuard::m_flAngerNoiseTime</targetSymbol>
    </ADDITIONALINFO>
    <PATH></PATH>
  </DEFECT>
  <DEFECT>
    <SFA>
      <FILEPATH>E:\XBLAH\content\Mapbase\klepto\src\game\server\hl2\</FILEPATH>
      <FILENAME>npc_antlionguard.cpp</FILENAME>
      <LINE>645</LINE>
      <COLUMN>19</COLUMN>
    </SFA>
    <DEFECTCODE>26495</DEFECTCODE>
    <DESCRIPTION>Variable 'CNPC_AntlionGuard::m_iChargeMisses' is uninitialized. Always initialize a member variable (type.6).</DESCRIPTION>
    <FUNCTION>CNPC_AntlionGuard::{ctor}</FUNCTION>
    <DECORATED>??0CNPC_AntlionGuard@@QAE@XZ</DECORATED>
    <FUNCLINE>645</FUNCLINE>
    <ADDITIONALINFO>
      <targetSymbol>CNPC_AntlionGuard::m_iChargeMisses</targetSymbol>
    </ADDITIONALINFO>
    <PATH></PATH>
  </DEFECT>
  <DEFECT>
    <SFA>
      <FILEPATH>E:\XBLAH\content\Mapbase\klepto\src\game\server\hl2\</FILEPATH>
      <FILENAME>npc_antlionguard.cpp</FILENAME>
      <LINE>645</LINE>
      <COLUMN>19</COLUMN>
    </SFA>
    <DEFECTCODE>26495</DEFECTCODE>
    <DESCRIPTION>Variable 'CNPC_AntlionGuard::m_bBarkEnabled' is uninitialized. Always initialize a member variable (type.6).</DESCRIPTION>
    <FUNCTION>CNPC_AntlionGuard::{ctor}</FUNCTION>
    <DECORATED>??0CNPC_AntlionGuard@@QAE@XZ</DECORATED>
    <FUNCLINE>645</FUNCLINE>
    <ADDITIONALINFO>
      <targetSymbol>CNPC_AntlionGuard::m_bBarkEnabled</targetSymbol>
    </ADDITIONALINFO>
    <PATH></PATH>
  </DEFECT>
  <DEFECT>
    <SFA>
      <FILEPATH>E:\XBLAH\content\Mapbase\klepto\src\game\server\hl2\</FILEPATH>
      <FILENAME>npc_antlionguard.cpp</FILENAME>
      <LINE>645</LINE>
      <COLUMN>19</COLUMN>
    </SFA>
    <DEFECTCODE>26495</DEFECTCODE>
    <DESCRIPTION>Variable 'CNPC_AntlionGuard::m_flSearchNoiseTime' is uninitialized. Always initialize a member variable (type.6).</DESCRIPTION>
    <FUNCTION>CNPC_AntlionGuard::{ctor}</FUNCTION>
    <DECORATED>??0CNPC_AntlionGuard@@QAE@XZ</DECORATED>
    <FUNCLINE>645</FUNCLINE>
    <ADDITIONALINFO>
      <targetSymbol>CNPC_AntlionGuard::m_flSearchNoiseTime</targetSymbol>
    </ADDITIONALINFO>
    <PATH></PATH>
  </DEFECT>
  <DEFECT>
    <SFA>
      <FILEPATH>E:\XBLAH\content\Mapbase\klepto\src\game\server\hl2\</FILEPATH>
      <FILENAME>npc_antlionguard.cpp</FILENAME>
      <LINE>645</LINE>
      <COLUMN>19</COLUMN>
    </SFA>
    <DEFECTCODE>26495</DEFECTCODE>
    <DESCRIPTION>Variable 'CNPC_AntlionGuard::m_flNextRoarTime' is uninitialized. Always initialize a member variable (type.6).</DESCRIPTION>
    <FUNCTION>CNPC_AntlionGuard::{ctor}</FUNCTION>
    <DECORATED>??0CNPC_AntlionGuard@@QAE@XZ</DECORATED>
    <FUNCLINE>645</FUNCLINE>
    <ADDITIONALINFO>
      <targetSymbol>CNPC_AntlionGuard::m_flNextRoarTime</targetSymbol>
    </ADDITIONALINFO>
    <PATH></PATH>
  </DEFECT>
  <DEFECT>
    <SFA>
      <FILEPATH>E:\XBLAH\content\Mapbase\klepto\src\game\server\hl2\</FILEPATH>
      <FILENAME>npc_antlionguard.cpp</FILENAME>
      <LINE>645</LINE>
      <COLUMN>19</COLUMN>
    </SFA>
    <DEFECTCODE>26495</DEFECTCODE>
    <DESCRIPTION>Variable 'CNPC_AntlionGuard::m_flNextSummonTime' is uninitialized. Always initialize a member variable (type.6).</DESCRIPTION>
    <FUNCTION>CNPC_AntlionGuard::{ctor}</FUNCTION>
    <DECORATED>??0CNPC_AntlionGuard@@QAE@XZ</DECORATED>
    <FUNCLINE>645</FUNCLINE>
    <ADDITIONALINFO>
      <targetSymbol>CNPC_AntlionGuard::m_flNextSummonTime</targetSymbol>
    </ADDITIONALINFO>
    <PATH></PATH>
  </DEFECT>
  <DEFECT>
    <SFA>
      <FILEPATH>E:\XBLAH\content\Mapbase\klepto\src\game\server\hl2\</FILEPATH>
      <FILENAME>npc_antlionguard.cpp</FILENAME>
      <LINE>645</LINE>
      <COLUMN>19</COLUMN>
    </SFA>
    <DEFECTCODE>26495</DEFECTCODE>
    <DESCRIPTION>Variable 'CNPC_AntlionGuard::m_bPreferPhysicsAttack' is uninitialized. Always initialize a member variable (type.6).</DESCRIPTION>
    <FUNCTION>CNPC_AntlionGuard::{ctor}</FUNCTION>
    <DECORATED>??0CNPC_AntlionGuard@@QAE@XZ</DECORATED>
    <FUNCLINE>645</FUNCLINE>
    <ADDITIONALINFO>
      <targetSymbol>CNPC_AntlionGuard::m_bPreferPhysicsAttack</targetSymbol>
    </ADDITIONALINFO>
    <PATH></PATH>
  </DEFECT>
  <DEFECT>
    <SFA>
      <FILEPATH>E:\XBLAH\content\Mapbase\klepto\src\game\server\hl2\</FILEPATH>
      <FILENAME>npc_antlionguard.cpp</FILENAME>
      <LINE>645</LINE>
      <COLUMN>19</COLUMN>
    </SFA>
    <DEFECTCODE>26495</DEFECTCODE>
    <DESCRIPTION>Variable 'CNPC_AntlionGuard::m_iNumLiveAntlions' is uninitialized. Always initialize a member variable (type.6).</DESCRIPTION>
    <FUNCTION>CNPC_AntlionGuard::{ctor}</FUNCTION>
    <DECORATED>??0CNPC_AntlionGuard@@QAE@XZ</DECORATED>
    <FUNCLINE>645</FUNCLINE>
    <ADDITIONALINFO>
      <targetSymbol>CNPC_AntlionGuard::m_iNumLiveAntlions</targetSymbol>
    </ADDITIONALINFO>
    <PATH></PATH>
  </DEFECT>
  <DEFECT>
    <SFA>
      <FILEPATH>E:\XBLAH\content\Mapbase\klepto\src\game\server\hl2\</FILEPATH>
      <FILENAME>npc_antlionguard.cpp</FILENAME>
      <LINE>645</LINE>
      <COLUMN>19</COLUMN>
    </SFA>
    <DEFECTCODE>26495</DEFECTCODE>
    <DESCRIPTION>Variable 'CNPC_AntlionGuard::m_pGrowlHighSound' is uninitialized. Always initialize a member variable (type.6).</DESCRIPTION>
    <FUNCTION>CNPC_AntlionGuard::{ctor}</FUNCTION>
    <DECORATED>??0CNPC_AntlionGuard@@QAE@XZ</DECORATED>
    <FUNCLINE>645</FUNCLINE>
    <ADDITIONALINFO>
      <targetSymbol>CNPC_AntlionGuard::m_pGrowlHighSound</targetSymbol>
    </ADDITIONALINFO>
    <PATH></PATH>
  </DEFECT>
  <DEFECT>
    <SFA>
      <FILEPATH>E:\XBLAH\content\Mapbase\klepto\src\game\server\hl2\</FILEPATH>
      <FILENAME>npc_antlionguard.cpp</FILENAME>
      <LINE>645</LINE>
      <COLUMN>19</COLUMN>
    </SFA>
    <DEFECTCODE>26495</DEFECTCODE>
    <DESCRIPTION>Variable 'CNPC_AntlionGuard::m_flChargeTime' is uninitialized. Always initialize a member variable (type.6).</DESCRIPTION>
    <FUNCTION>CNPC_AntlionGuard::{ctor}</FUNCTION>
    <DECORATED>??0CNPC_AntlionGuard@@QAE@XZ</DECORATED>
    <FUNCLINE>645</FUNCLINE>
    <ADDITIONALINFO>
      <targetSymbol>CNPC_AntlionGuard::m_flChargeTime</targetSymbol>
    </ADDITIONALINFO>
    <PATH></PATH>
  </DEFECT>
  <DEFECT>
    <SFA>
      <FILEPATH>E:\XBLAH\content\Mapbase\klepto\src\game\server\hl2\</FILEPATH>
      <FILENAME>npc_antlionguard.cpp</FILENAME>
      <LINE>645</LINE>
      <COLUMN>19</COLUMN>
    </SFA>
    <DEFECTCODE>26495</DEFECTCODE>
    <DESCRIPTION>Variable 'CNPC_AntlionGuard::m_pConfusedSound' is uninitialized. Always initialize a member variable (type.6).</DESCRIPTION>
    <FUNCTION>CNPC_AntlionGuard::{ctor}</FUNCTION>
    <DECORATED>??0CNPC_AntlionGuard@@QAE@XZ</DECORATED>
    <FUNCLINE>645</FUNCLINE>
    <ADDITIONALINFO>
      <targetSymbol>CNPC_AntlionGuard::m_pConfusedSound</targetSymbol>
    </ADDITIONALINFO>
    <PATH></PATH>
  </DEFECT>
  <DEFECT>
    <SFA>
      <FILEPATH>E:\XBLAH\content\Mapbase\klepto\src\game\server\hl2\</FILEPATH>
      <FILENAME>npc_antlionguard.cpp</FILENAME>
      <LINE>645</LINE>
      <COLUMN>19</COLUMN>
    </SFA>
    <DEFECTCODE>26495</DEFECTCODE>
    <DESCRIPTION>Variable 'CNPC_AntlionGuard::m_bStopped' is uninitialized. Always initialize a member variable (type.6).</DESCRIPTION>
    <FUNCTION>CNPC_AntlionGuard::{ctor}</FUNCTION>
    <DECORATED>??0CNPC_AntlionGuard@@QAE@XZ</DECORATED>
    <FUNCLINE>645</FUNCLINE>
    <ADDITIONALINFO>
      <targetSymbol>CNPC_AntlionGuard::m_bStopped</targetSymbol>
    </ADDITIONALINFO>
    <PATH></PATH>
  </DEFECT>
  <DEFECT>
    <SFA>
      <FILEPATH>E:\XBLAH\content\Mapbase\klepto\src\game\server\hl2\</FILEPATH>
      <FILENAME>npc_antlionguard.cpp</FILENAME>
      <LINE>645</LINE>
      <COLUMN>19</COLUMN>
    </SFA>
    <DEFECTCODE>26495</DEFECTCODE>
    <DESCRIPTION>Variable 'CNPC_AntlionGuard::m_poseThrow' is uninitialized. Always initialize a member variable (type.6).</DESCRIPTION>
    <FUNCTION>CNPC_AntlionGuard::{ctor}</FUNCTION>
    <DECORATED>??0CNPC_AntlionGuard@@QAE@XZ</DECORATED>
    <FUNCLINE>645</FUNCLINE>
    <ADDITIONALINFO>
      <targetSymbol>CNPC_AntlionGuard::m_poseThrow</targetSymbol>
    </ADDITIONALINFO>
    <PATH></PATH>
  </DEFECT>
  <DEFECT>
    <SFA>
      <FILEPATH>E:\XBLAH\content\Mapbase\klepto\src\game\server\hl2\</FILEPATH>
      <FILENAME>npc_antlionguard.cpp</FILENAME>
      <LINE>645</LINE>
      <COLUMN>19</COLUMN>
    </SFA>
    <DEFECTCODE>26495</DEFECTCODE>
    <DESCRIPTION>Variable 'CNPC_AntlionGuard::m_poseHead_Yaw' is uninitialized. Always initialize a member variable (type.6).</DESCRIPTION>
    <FUNCTION>CNPC_AntlionGuard::{ctor}</FUNCTION>
    <DECORATED>??0CNPC_AntlionGuard@@QAE@XZ</DECORATED>
    <FUNCLINE>645</FUNCLINE>
    <ADDITIONALINFO>
      <targetSymbol>CNPC_AntlionGuard::m_poseHead_Yaw</targetSymbol>
    </ADDITIONALINFO>
    <PATH></PATH>
  </DEFECT>
  <DEFECT>
    <SFA>
      <FILEPATH>E:\XBLAH\content\Mapbase\klepto\src\game\server\hl2\</FILEPATH>
      <FILENAME>npc_antlionguard.cpp</FILENAME>
      <LINE>645</LINE>
      <COLUMN>19</COLUMN>
    </SFA>
    <DEFECTCODE>26495</DEFECTCODE>
    <DESCRIPTION>Variable 'CNPC_AntlionGuard::m_poseHead_Pitch' is uninitialized. Always initialize a member variable (type.6).</DESCRIPTION>
    <FUNCTION>CNPC_AntlionGuard::{ctor}</FUNCTION>
    <DECORATED>??0CNPC_AntlionGuard@@QAE@XZ</DECORATED>
    <FUNCLINE>645</FUNCLINE>
    <ADDITIONALINFO>
      <targetSymbol>CNPC_AntlionGuard::m_poseHead_Pitch</targetSymbol>
    </ADDITIONALINFO>
    <PATH></PATH>
  </DEFECT>
  <DEFECT>
    <SFA>
      <FILEPATH>E:\XBLAH\content\Mapbase\klepto\src\game\server\hl2\</FILEPATH>
      <FILENAME>npc_antlionguard.cpp</FILENAME>
      <LINE>228</LINE>
      <COLUMN>0</COLUMN>
    </SFA>
    <DEFECTCODE>26495</DEFECTCODE>
    <DESCRIPTION>Variable 'PhysicsObjectCriteria_t::pTarget' is uninitialized. Always initialize a member variable (type.6).</DESCRIPTION>
    <FUNCTION>PhysicsObjectCriteria_t::{ctor}</FUNCTION>
    <DECORATED>??0PhysicsObjectCriteria_t@@QAE@XZ</DECORATED>
    <FUNCLINE>228</FUNCLINE>
    <ADDITIONALINFO>
      <targetSymbol>PhysicsObjectCriteria_t::pTarget</targetSymbol>
    </ADDITIONALINFO>
    <PATH></PATH>
  </DEFECT>
  <DEFECT>
    <SFA>
      <FILEPATH>E:\XBLAH\content\Mapbase\klepto\src\game\server\hl2\</FILEPATH>
      <FILENAME>npc_antlionguard.cpp</FILENAME>
      <LINE>228</LINE>
      <COLUMN>0</COLUMN>
    </SFA>
    <DEFECTCODE>26495</DEFECTCODE>
    <DESCRIPTION>Variable 'PhysicsObjectCriteria_t::flRadius' is uninitialized. Always initialize a member variable (type.6).</DESCRIPTION>
    <FUNCTION>PhysicsObjectCriteria_t::{ctor}</FUNCTION>
    <DECORATED>??0PhysicsObjectCriteria_t@@QAE@XZ</DECORATED>
    <FUNCLINE>228</FUNCLINE>
    <ADDITIONALINFO>
      <targetSymbol>PhysicsObjectCriteria_t::flRadius</targetSymbol>
    </ADDITIONALINFO>
    <PATH></PATH>
  </DEFECT>
  <DEFECT>
    <SFA>
      <FILEPATH>E:\XBLAH\content\Mapbase\klepto\src\game\server\hl2\</FILEPATH>
      <FILENAME>npc_antlionguard.cpp</FILENAME>
      <LINE>228</LINE>
      <COLUMN>0</COLUMN>
    </SFA>
    <DEFECTCODE>26495</DEFECTCODE>
    <DESCRIPTION>Variable 'PhysicsObjectCriteria_t::flTargetCone' is uninitialized. Always initialize a member variable (type.6).</DESCRIPTION>
    <FUNCTION>PhysicsObjectCriteria_t::{ctor}</FUNCTION>
    <DECORATED>??0PhysicsObjectCriteria_t@@QAE@XZ</DECORATED>
    <FUNCLINE>228</FUNCLINE>
    <ADDITIONALINFO>
      <targetSymbol>PhysicsObjectCriteria_t::flTargetCone</targetSymbol>
    </ADDITIONALINFO>
    <PATH></PATH>
  </DEFECT>
  <DEFECT>
    <SFA>
      <FILEPATH>E:\XBLAH\content\Mapbase\klepto\src\game\server\hl2\</FILEPATH>
      <FILENAME>npc_antlionguard.cpp</FILENAME>
      <LINE>228</LINE>
      <COLUMN>0</COLUMN>
    </SFA>
    <DEFECTCODE>26495</DEFECTCODE>
    <DESCRIPTION>Variable 'PhysicsObjectCriteria_t::bPreferObjectsAlongTargetVector' is uninitialized. Always initialize a member variable (type.6).</DESCRIPTION>
    <FUNCTION>PhysicsObjectCriteria_t::{ctor}</FUNCTION>
    <DECORATED>??0PhysicsObjectCriteria_t@@QAE@XZ</DECORATED>
    <FUNCLINE>228</FUNCLINE>
    <ADDITIONALINFO>
      <targetSymbol>PhysicsObjectCriteria_t::bPreferObjectsAlongTargetVector</targetSymbol>
    </ADDITIONALINFO>
    <PATH></PATH>
  </DEFECT>
  <DEFECT>
    <SFA>
      <FILEPATH>E:\XBLAH\content\Mapbase\klepto\src\game\server\hl2\</FILEPATH>
      <FILENAME>npc_antlionguard.cpp</FILENAME>
      <LINE>228</LINE>
      <COLUMN>0</COLUMN>
    </SFA>
    <DEFECTCODE>26495</DEFECTCODE>
    <DESCRIPTION>Variable 'PhysicsObjectCriteria_t::flNearRadius' is uninitialized. Always initialize a member variable (type.6).</DESCRIPTION>
    <FUNCTION>PhysicsObjectCriteria_t::{ctor}</FUNCTION>
    <DECORATED>??0PhysicsObjectCriteria_t@@QAE@XZ</DECORATED>
    <FUNCLINE>228</FUNCLINE>
    <ADDITIONALINFO>
      <targetSymbol>PhysicsObjectCriteria_t::flNearRadius</targetSymbol>
    </ADDITIONALINFO>
    <PATH></PATH>
  </DEFECT>
  <DEFECT>
    <SFA>
      <FILEPATH>E:\XBLAH\content\Mapbase\klepto\src\game\server\hl2\</FILEPATH>
      <FILENAME>npc_antlionguard.cpp</FILENAME>
      <LINE>3866</LINE>
      <COLUMN>20</COLUMN>
    </SFA>
    <DEFECTCODE>6011</DEFECTCODE>
    <DESCRIPTION>Dereferencing NULL pointer 'pOut'. </DESCRIPTION>
    <FUNCTION>CNPC_AntlionGuard::CanStandAtPoint</FUNCTION>
    <DECORATED>?CanStandAtPoint@CNPC_AntlionGuard@@AAE_NABVVector@@PAV2@@Z</DECORATED>
    <FUNCLINE>3825</FUNCLINE>
    <PROBABILITY>1</PROBABILITY>
    <RANK>4</RANK>
    <CATEGORY>
      <RULECATEGORY>mspft</RULECATEGORY>
    </CATEGORY>
    <PATH>
      <SFA>
        <FILEPATH>E:\XBLAH\content\Mapbase\klepto\src\game\server\hl2\</FILEPATH>
        <FILENAME>npc_antlionguard.cpp</FILENAME>
        <LINE>3827</LINE>
        <COLUMN>8</COLUMN>
      </SFA>
      <SFA>
        <FILEPATH>E:\XBLAH\content\Mapbase\klepto\src\game\server\hl2\</FILEPATH>
        <FILENAME>npc_antlionguard.cpp</FILENAME>
        <LINE>3828</LINE>
        <COLUMN>8</COLUMN>
      </SFA>
      <SFA>
        <FILEPATH>E:\XBLAH\content\Mapbase\klepto\src\game\server\hl2\</FILEPATH>
        <FILENAME>npc_antlionguard.cpp</FILENAME>
        <LINE>3829</LINE>
        <COLUMN>9</COLUMN>
      </SFA>
      <SFA>
        <FILEPATH>E:\XBLAH\content\Mapbase\klepto\src\game\server\hl2\</FILEPATH>
        <FILENAME>npc_antlionguard.cpp</FILENAME>
        <LINE>3830</LINE>
        <COLUMN>6</COLUMN>
      </SFA>
      <SFA>
        <FILEPATH>E:\XBLAH\content\Mapbase\klepto\src\game\server\hl2\</FILEPATH>
        <FILENAME>npc_antlionguard.cpp</FILENAME>
        <LINE>3834</LINE>
        <COLUMN>15</COLUMN>
      </SFA>
      <SFA>
        <FILEPATH>E:\XBLAH\content\Mapbase\klepto\src\game\server\hl2\</FILEPATH>
        <FILENAME>npc_antlionguard.cpp</FILENAME>
        <LINE>3835</LINE>
        <COLUMN>20</COLUMN>
      </SFA>
      <SFA>
        <FILEPATH>E:\XBLAH\content\Mapbase\klepto\src\game\server\hl2\</FILEPATH>
        <FILENAME>npc_antlionguard.cpp</FILENAME>
        <LINE>3846</LINE>
        <COLUMN>16</COLUMN>
      </SFA>
      <SFA>
        <FILEPATH>E:\XBLAH\content\Mapbase\klepto\src\game\server\hl2\</FILEPATH>
        <FILENAME>npc_antlionguard.cpp</FILENAME>
        <LINE>3850</LINE>
        <COLUMN>20</COLUMN>
      </SFA>
      <SFA>
        <FILEPATH>E:\XBLAH\content\Mapbase\klepto\src\game\server\hl2\</FILEPATH>
        <FILENAME>npc_antlionguard.cpp</FILENAME>
        <LINE>3859</LINE>
        <COLUMN>6</COLUMN>
        <KEYEVENT>
          <ID>1</ID>
          <KIND>branch</KIND>
          <IMPORTANCE>Full</IMPORTANCE>
          <MESSAGE>'pOut' may be NULL (Skip this branch)</MESSAGE>
        </KEYEVENT>
      </SFA>
      <SFA>
        <FILEPATH>E:\XBLAH\content\Mapbase\klepto\src\game\server\hl2\</FILEPATH>
        <FILENAME>npc_antlionguard.cpp</FILENAME>
        <LINE>3864</LINE>
        <COLUMN>36</COLUMN>
        <KEYEVENT>
          <ID>2</ID>
          <KIND>branch</KIND>
          <IMPORTANCE>Full</IMPORTANCE>
          <MESSAGE>Enter this branch, (assume '&lt;branch condition&gt;')</MESSAGE>
        </KEYEVENT>
      </SFA>
      <SFA>
        <FILEPATH>E:\XBLAH\content\Mapbase\klepto\src\game\server\hl2\</FILEPATH>
        <FILENAME>npc_antlionguard.cpp</FILENAME>
        <LINE>3866</LINE>
        <COLUMN>20</COLUMN>
        <KEYEVENT>
          <ID>3</ID>
          <KIND>usage</KIND>
          <IMPORTANCE>Essential</IMPORTANCE>
          <MESSAGE>'pOut' is dereferenced, but may still be NULL</MESSAGE>
        </KEYEVENT>
      </SFA>
    </PATH>
  </DEFECT>
  <DEFECT>
    <SFA>
      <FILEPATH>E:\XBLAH\content\Mapbase\klepto\src\public\tier1\</FILEPATH>
      <FILENAME>utlvector.h</FILENAME>
      <LINE>920</LINE>
      <COLUMN>13</COLUMN>
    </SFA>
    <DEFECTCODE>6011</DEFECTCODE>
    <DESCRIPTION>Dereferencing NULL pointer 'pArray'. </DESCRIPTION>
    <FUNCTION>CUtlVector&lt;CAI_Hint *,CUtlMemory&lt;CAI_Hint *,int&gt; &gt;::CopyArray</FUNCTION>
    <DECORATED>?CopyArray@?$CUtlVector@PAVCAI_Hint@@V?$CUtlMemory@PAVCAI_Hint@@H@@@@QAEXPBQAVCAI_Hint@@H@Z</DECORATED>
    <FUNCLINE>912</FUNCLINE>
    <PROBABILITY>1</PROBABILITY>
    <RANK>4</RANK>
    <CATEGORY>
      <RULECATEGORY>mspft</RULECATEGORY>
    </CATEGORY>
    <PATH>
      <SFA>
        <FILEPATH>E:\XBLAH\content\Mapbase\klepto\src\public\tier1\</FILEPATH>
        <FILENAME>utlvector.h</FILENAME>
        <LINE>915</LINE>
        <COLUMN>1</COLUMN>
        <KEYEVENT>
          <ID>1</ID>
          <KIND>declaration</KIND>
          <IMPORTANCE>Essential</IMPORTANCE>
          <MESSAGE>'pArray' may be NULL</MESSAGE>
        </KEYEVENT>
      </SFA>
      <SFA>
        <FILEPATH>E:\XBLAH\content\Mapbase\klepto\src\public\tier1\</FILEPATH>
        <FILENAME>utlvector.h</FILENAME>
        <LINE>917</LINE>
        <COLUMN>8</COLUMN>
      </SFA>
      <SFA>
        <FILEPATH>E:\XBLAH\content\Mapbase\klepto\src\public\tier1\</FILEPATH>
        <FILENAME>utlvector.h</FILENAME>
        <LINE>918</LINE>
        <COLUMN>10</COLUMN>
      </SFA>
      <SFA>
        <FILEPATH>E:\XBLAH\content\Mapbase\klepto\src\public\tier1\</FILEPATH>
        <FILENAME>utlvector.h</FILENAME>
        <LINE>918</LINE>
        <COLUMN>17</COLUMN>
        <KEYEVENT>
          <ID>2</ID>
          <KIND>branch</KIND>
          <IMPORTANCE>Full</IMPORTANCE>
          <MESSAGE>Enter this loop, (assume 'i&lt;size')</MESSAGE>
        </KEYEVENT>
      </SFA>
      <SFA>
        <FILEPATH>E:\XBLAH\content\Mapbase\klepto\src\public\tier1\</FILEPATH>
        <FILENAME>utlvector.h</FILENAME>
        <LINE>920</LINE>
        <COLUMN>13</COLUMN>
        <KEYEVENT>
          <ID>3</ID>
          <KIND>usage</KIND>
          <IMPORTANCE>Essential</IMPORTANCE>
          <MESSAGE>'pArray' is dereferenced, but may still be NULL</MESSAGE>
        </KEYEVENT>
      </SFA>
    </PATH>
  </DEFECT>
  <DEFECT>
    <SFA>
      <FILEPATH>E:\XBLAH\content\Mapbase\klepto\src\public\tier1\</FILEPATH>
      <FILENAME>utlmemory.h</FILENAME>
      <LINE>210</LINE>
      <COLUMN>1</COLUMN>
    </SFA>
    <DEFECTCODE>26495</DEFECTCODE>
    <DESCRIPTION>Variable 'CUtlMemoryFixed&lt;CHandle&lt;CBaseEntity&gt;,8,0&gt;::m_Memory' is uninitialized. Always initialize a member variable (type.6).</DESCRIPTION>
    <FUNCTION>CUtlMemoryFixed&lt;CHandle&lt;CBaseEntity&gt;,8,0&gt;::{ctor}</FUNCTION>
    <DECORATED>??0?$CUtlMemoryFixed@V?$CHandle@VCBaseEntity@@@@$07$0A@@@QAE@HH@Z</DECORATED>
    <FUNCLINE>210</FUNCLINE>
    <ADDITIONALINFO>
      <targetSymbol>CUtlMemoryFixed&lt;CHandle&lt;CBaseEntity&gt;,8,0&gt;::m_Memory</targetSymbol>
    </ADDITIONALINFO>
    <PATH></PATH>
  </DEFECT>
</DEFECTS>