<?xml version="1.0" encoding="UTF-8"?>
<DEFECTS>
  <DEFECT>
    <SFA>
      <FILEPATH>E:\XBLAH\content\Mapbase\klepto\src\public\vphysics\</FILEPATH>
      <FILENAME>constraints.h</FILENAME>
      <LINE>144</LINE>
      <COLUMN>0</COLUMN>
    </SFA>
    <DEFECTCODE>26495</DEFECTCODE>
    <DESCRIPTION>Variable 'constraint_hingeparams_t::constraint' is uninitialized. Always initialize a member variable (type.6).</DESCRIPTION>
    <FUNCTION>constraint_hingeparams_t::{ctor}</FUNCTION>
    <DECORATED>??0constraint_hingeparams_t@@QAE@XZ</DECORATED>
    <FUNCLINE>144</FUNCLINE>
    <ADDITIONALINFO>
      <targetSymbol>constraint_hingeparams_t::constraint</targetSymbol>
    </ADDITIONALINFO>
    <PATH></PATH>
  </DEFECT>
  <DEFECT>
    <SFA>
      <FILEPATH>E:\XBLAH\content\Mapbase\klepto\src\public\vphysics\</FILEPATH>
      <FILENAME>constraints.h</FILENAME>
      <LINE>144</LINE>
      <COLUMN>0</COLUMN>
    </SFA>
    <DEFECTCODE>26495</DEFECTCODE>
    <DESCRIPTION>Variable 'constraint_hingeparams_t::hingeAxis' is uninitialized. Always initialize a member variable (type.6).</DESCRIPTION>
    <FUNCTION>constraint_hingeparams_t::{ctor}</FUNCTION>
    <DECORATED>??0constraint_hingeparams_t@@QAE@XZ</DECORATED>
    <FUNCLINE>144</FUNCLINE>
    <ADDITIONALINFO>
      <targetSymbol>constraint_hingeparams_t::hingeAxis</targetSymbol>
    </ADDITIONALINFO>
    <PATH></PATH>
  </DEFECT>
  <DEFECT>
    <SFA>
      <FILEPATH>E:\XBLAH\content\Mapbase\klepto\src\game\server\hl2\</FILEPATH>
      <FILENAME>weapon_frag.cpp</FILENAME>
      <LINE>112</LINE>
      <COLUMN>13</COLUMN>
    </SFA>
    <DEFECTCODE>26495</DEFECTCODE>
    <DESCRIPTION>Variable 'CWeaponFrag::m_fDrawbackFinished' is uninitialized. Always initialize a member variable (type.6).</DESCRIPTION>
    <FUNCTION>CWeaponFrag::{ctor}</FUNCTION>
    <DECORATED>??0CWeaponFrag@@QAE@XZ</DECORATED>
    <FUNCLINE>112</FUNCLINE>
    <ADDITIONALINFO>
      <targetSymbol>CWeaponFrag::m_fDrawbackFinished</targetSymbol>
    </ADDITIONALINFO>
    <PATH></PATH>
  </DEFECT>
  <DEFECT>
    <SFA>
      <FILEPATH>E:\XBLAH\content\Mapbase\klepto\src\game\server\hl2\</FILEPATH>
      <FILENAME>weapon_frag.cpp</FILENAME>
      <LINE>112</LINE>
      <COLUMN>13</COLUMN>
    </SFA>
    <DEFECTCODE>26495</DEFECTCODE>
    <DESCRIPTION>Variable 'CWeaponFrag::m_AttackPaused' is uninitialized. Always initialize a member variable (type.6).</DESCRIPTION>
    <FUNCTION>CWeaponFrag::{ctor}</FUNCTION>
    <DECORATED>??0CWeaponFrag@@QAE@XZ</DECORATED>
    <FUNCLINE>112</FUNCLINE>
    <ADDITIONALINFO>
      <targetSymbol>CWeaponFrag::m_AttackPaused</targetSymbol>
    </ADDITIONALINFO>
    <PATH></PATH>
  </DEFECT>
  <DEFECT>
    <SFA>
      <FILEPATH>E:\XBLAH\content\Mapbase\klepto\src\game\shared\hl2\</FILEPATH>
      <FILENAME>basehlcombatweapon_shared.h</FILENAME>
      <LINE>64</LINE>
      <COLUMN>0</COLUMN>
    </SFA>
    <DEFECTCODE>26495</DEFECTCODE>
    <DESCRIPTION>Variable 'CBaseHLCombatWeapon::m_iPrimaryAttacks' is uninitialized. Always initialize a member variable (type.6).</DESCRIPTION>
    <FUNCTION>CBaseHLCombatWeapon::{ctor}</FUNCTION>
    <DECORATED>??0CBaseHLCombatWeapon@@QAE@XZ</DECORATED>
    <FUNCLINE>64</FUNCLINE>
    <ADDITIONALINFO>
      <targetSymbol>CBaseHLCombatWeapon::m_iPrimaryAttacks</targetSymbol>
    </ADDITIONALINFO>
    <PATH></PATH>
  </DEFECT>
  <DEFECT>
    <SFA>
      <FILEPATH>E:\XBLAH\content\Mapbase\klepto\src\game\shared\hl2\</FILEPATH>
      <FILENAME>basehlcombatweapon_shared.h</FILENAME>
      <LINE>64</LINE>
      <COLUMN>0</COLUMN>
    </SFA>
    <DEFECTCODE>26495</DEFECTCODE>
    <DESCRIPTION>Variable 'CBaseHLCombatWeapon::m_iSecondaryAttacks' is uninitialized. Always initialize a member variable (type.6).</DESCRIPTION>
    <FUNCTION>CBaseHLCombatWeapon::{ctor}</FUNCTION>
    <DECORATED>??0CBaseHLCombatWeapon@@QAE@XZ</DECORATED>
    <FUNCLINE>64</FUNCLINE>
    <ADDITIONALINFO>
      <targetSymbol>CBaseHLCombatWeapon::m_iSecondaryAttacks</targetSymbol>
    </ADDITIONALINFO>
    <PATH></PATH>
  </DEFECT>
  <DEFECT>
    <SFA>
      <FILEPATH>E:\XBLAH\content\Mapbase\klepto\src\game\shared\hl2\</FILEPATH>
      <FILENAME>basehlcombatweapon_shared.h</FILENAME>
      <LINE>64</LINE>
      <COLUMN>0</COLUMN>
    </SFA>
    <DEFECTCODE>26495</DEFECTCODE>
    <DESCRIPTION>Variable 'CBaseHLCombatWeapon::m_bLowered' is uninitialized. Always initialize a member variable (type.6).</DESCRIPTION>
    <FUNCTION>CBaseHLCombatWeapon::{ctor}</FUNCTION>
    <DECORATED>??0CBaseHLCombatWeapon@@QAE@XZ</DECORATED>
    <FUNCLINE>64</FUNCLINE>
    <ADDITIONALINFO>
      <targetSymbol>CBaseHLCombatWeapon::m_bLowered</targetSymbol>
    </ADDITIONALINFO>
    <PATH></PATH>
  </DEFECT>
  <DEFECT>
    <SFA>
      <FILEPATH>E:\XBLAH\content\Mapbase\klepto\src\game\shared\hl2\</FILEPATH>
      <FILENAME>basehlcombatweapon_shared.h</FILENAME>
      <LINE>64</LINE>
      <COLUMN>0</COLUMN>
    </SFA>
    <DEFECTCODE>26495</DEFECTCODE>
    <DESCRIPTION>Variable 'CBaseHLCombatWeapon::m_flRaiseTime' is uninitialized. Always initialize a member variable (type.6).</DESCRIPTION>
    <FUNCTION>CBaseHLCombatWeapon::{ctor}</FUNCTION>
    <DECORATED>??0CBaseHLCombatWeapon@@QAE@XZ</DECORATED>
    <FUNCLINE>64</FUNCLINE>
    <ADDITIONALINFO>
      <targetSymbol>CBaseHLCombatWeapon::m_flRaiseTime</targetSymbol>
    </ADDITIONALINFO>
    <PATH></PATH>
  </DEFECT>
  <DEFECT>
    <SFA>
      <FILEPATH>E:\XBLAH\content\Mapbase\klepto\src\game\shared\hl2\</FILEPATH>
      <FILENAME>basehlcombatweapon_shared.h</FILENAME>
      <LINE>64</LINE>
      <COLUMN>0</COLUMN>
    </SFA>
    <DEFECTCODE>26495</DEFECTCODE>
    <DESCRIPTION>Variable 'CBaseHLCombatWeapon::m_flHolsterTime' is uninitialized. Always initialize a member variable (type.6).</DESCRIPTION>
    <FUNCTION>CBaseHLCombatWeapon::{ctor}</FUNCTION>
    <DECORATED>??0CBaseHLCombatWeapon@@QAE@XZ</DECORATED>
    <FUNCLINE>64</FUNCLINE>
    <ADDITIONALINFO>
      <targetSymbol>CBaseHLCombatWeapon::m_flHolsterTime</targetSymbol>
    </ADDITIONALINFO>
    <PATH></PATH>
  </DEFECT>
</DEFECTS>